{
"meta":{"test_sets":[],"test_metrics":[],"learn_metrics":[{"best_value":"Min","name":"Logloss"}],"launch_mode":"Train","parameters":"","iteration_count":1000,"learn_sets":["learn"],"name":"experiment"},
"iterations":[
{"learn":[0.6266761078],"iteration":0,"passed_time":0.01918620833,"remaining_time":19.16702213},
{"learn":[0.5750204678],"iteration":1,"passed_time":0.03622254167,"remaining_time":18.07504829},
{"learn":[0.5369152031],"iteration":2,"passed_time":0.05381625,"remaining_time":17.88493375},
{"learn":[0.5081660941],"iteration":3,"passed_time":0.07403420833,"remaining_time":18.43451788},
{"learn":[0.4818944864],"iteration":4,"passed_time":0.09272091667,"remaining_time":18.45146242},
{"learn":[0.4606220591],"iteration":5,"passed_time":0.1128349583,"remaining_time":18.69299143},
{"learn":[0.4387029206],"iteration":6,"passed_time":0.1314479167,"remaining_time":18.64682589},
{"learn":[0.4251918116],"iteration":7,"passed_time":0.1494800417,"remaining_time":18.53552517},
{"learn":[0.4098153575],"iteration":8,"passed_time":0.1688813333,"remaining_time":18.59571126},
{"learn":[0.3988773237],"iteration":9,"passed_time":0.1882555417,"remaining_time":18.63729862},
{"learn":[0.3872331971],"iteration":10,"passed_time":0.2106797083,"remaining_time":18.94202105},
{"learn":[0.3774407766],"iteration":11,"passed_time":0.231359125,"remaining_time":19.04856796},
{"learn":[0.3704477977],"iteration":12,"passed_time":0.2492285833,"remaining_time":18.9222009},
{"learn":[0.364732374],"iteration":13,"passed_time":0.2658364167,"remaining_time":18.72247906},
{"learn":[0.3587466942],"iteration":14,"passed_time":0.2834887917,"remaining_time":18.61576399},
{"learn":[0.3540576751],"iteration":15,"passed_time":0.3007320417,"remaining_time":18.49502056},
{"learn":[0.3483064765],"iteration":16,"passed_time":0.3216797917,"remaining_time":18.60066089},
{"learn":[0.344764816],"iteration":17,"passed_time":0.337871875,"remaining_time":18.43278785},
{"learn":[0.3406527687],"iteration":18,"passed_time":0.3592420417,"remaining_time":18.54823384},
{"learn":[0.3348256495],"iteration":19,"passed_time":0.3806754167,"remaining_time":18.65309542},
{"learn":[0.3308416596],"iteration":20,"passed_time":0.4017133333,"remaining_time":18.72749302},
{"learn":[0.3248853235],"iteration":21,"passed_time":0.4244177917,"remaining_time":18.86730001},
{"learn":[0.3208512369],"iteration":22,"passed_time":0.4445604167,"remaining_time":18.88415335},
{"learn":[0.3175430795],"iteration":23,"passed_time":0.4642485,"remaining_time":18.879439},
{"learn":[0.3141800493],"iteration":24,"passed_time":0.4826253333,"remaining_time":18.822388},
{"learn":[0.3107451088],"iteration":25,"passed_time":0.5068622083,"remaining_time":18.98783811},
{"learn":[0.306989231],"iteration":26,"passed_time":0.5219562917,"remaining_time":18.80975821},
{"learn":[0.3048853202],"iteration":27,"passed_time":0.537673125,"remaining_time":18.66493848},
{"learn":[0.3036376362],"iteration":28,"passed_time":0.5502265,"remaining_time":18.42310109},
{"learn":[0.3009727606],"iteration":29,"passed_time":0.5704377917,"remaining_time":18.44415526},
{"learn":[0.297489707],"iteration":30,"passed_time":0.5917425833,"remaining_time":18.49672785},
{"learn":[0.2948373264],"iteration":31,"passed_time":0.6120917083,"remaining_time":18.51577418},
{"learn":[0.2930543162],"iteration":32,"passed_time":0.6290661667,"remaining_time":18.43354494},
{"learn":[0.2903604955],"iteration":33,"passed_time":0.6472919167,"remaining_time":18.39070563},
{"learn":[0.2885308773],"iteration":34,"passed_time":0.6656875833,"remaining_time":18.35395765},
{"learn":[0.2854295215],"iteration":35,"passed_time":0.68440975,"remaining_time":18.32697219},
{"learn":[0.2829972678],"iteration":36,"passed_time":0.7043246667,"remaining_time":18.33147714},
{"learn":[0.2811173875],"iteration":37,"passed_time":0.7243642917,"remaining_time":18.33785391},
{"learn":[0.2798353793],"iteration":38,"passed_time":0.73694625,"remaining_time":18.15911144},
{"learn":[0.2783300835],"iteration":39,"passed_time":0.7550034167,"remaining_time":18.120082},
{"learn":[0.2760262558],"iteration":40,"passed_time":0.7707707917,"remaining_time":18.02851681},
{"learn":[0.2736739036],"iteration":41,"passed_time":0.7918525833,"remaining_time":18.06178035},
{"learn":[0.2719521726],"iteration":42,"passed_time":0.80997825,"remaining_time":18.02672524},
{"learn":[0.2701441075],"iteration":43,"passed_time":0.8305406667,"remaining_time":18.04538358},
{"learn":[0.2689950814],"iteration":44,"passed_time":0.8475132917,"remaining_time":17.98611541},
{"learn":[0.2669800134],"iteration":45,"passed_time":0.8714255,"remaining_time":18.07260711},
{"learn":[0.2646822438],"iteration":46,"passed_time":0.8933198333,"remaining_time":18.11348513},
{"learn":[0.26150535],"iteration":47,"passed_time":0.9147043333,"remaining_time":18.14163594},
{"learn":[0.2589521332],"iteration":48,"passed_time":0.9382908333,"remaining_time":18.21050168},
{"learn":[0.2574632247],"iteration":49,"passed_time":0.95784225,"remaining_time":18.19900275},
{"learn":[0.2558937054],"iteration":50,"passed_time":0.9767961667,"remaining_time":18.17606985},
{"learn":[0.2531043285],"iteration":51,"passed_time":1.000430417,"remaining_time":18.23861606},
{"learn":[0.2507545071],"iteration":52,"passed_time":1.021991875,"remaining_time":18.26087369},
{"learn":[0.2488208725],"iteration":53,"passed_time":1.04447425,"remaining_time":18.29764149},
{"learn":[0.2480118802],"iteration":54,"passed_time":1.057849667,"remaining_time":18.17578064},
{"learn":[0.2467404767],"iteration":55,"passed_time":1.0775475,"remaining_time":18.16437214},
{"learn":[0.2455113135],"iteration":56,"passed_time":1.095310292,"remaining_time":18.12065974},
{"learn":[0.2432299594],"iteration":57,"passed_time":1.118075792,"remaining_time":18.15909303},
{"learn":[0.2421319802],"iteration":58,"passed_time":1.136723333,"remaining_time":18.12977384},
{"learn":[0.241085937],"iteration":59,"passed_time":1.155084792,"remaining_time":18.0963284},
{"learn":[0.2391895458],"iteration":60,"passed_time":1.175762708,"remaining_time":18.09903579},
{"learn":[0.2380527123],"iteration":61,"passed_time":1.193171958,"remaining_time":18.05153705},
{"learn":[0.2363182833],"iteration":62,"passed_time":1.211551833,"remaining_time":18.01942965},
{"learn":[0.2347117392],"iteration":63,"passed_time":1.232384083,"remaining_time":18.02361722},
{"learn":[0.2335115365],"iteration":64,"passed_time":1.252610542,"remaining_time":18.01832087},
{"learn":[0.2321619056],"iteration":65,"passed_time":1.273093292,"remaining_time":18.01619901},
{"learn":[0.2312524228],"iteration":66,"passed_time":1.292947458,"remaining_time":18.0047758},
{"learn":[0.2301886328],"iteration":67,"passed_time":1.313249167,"remaining_time":17.99923858},
{"learn":[0.2289328547],"iteration":68,"passed_time":1.334931792,"remaining_time":18.01190577},
{"learn":[0.2272679325],"iteration":69,"passed_time":1.356159292,"remaining_time":18.01754488},
{"learn":[0.2264755629],"iteration":70,"passed_time":1.374214292,"remaining_time":17.98091658},
{"learn":[0.2248845008],"iteration":71,"passed_time":1.3955015,"remaining_time":17.98646378},
{"learn":[0.2232816875],"iteration":72,"passed_time":1.417512042,"remaining_time":18.00046113},
{"learn":[0.2220849333],"iteration":73,"passed_time":1.438912875,"remaining_time":18.00585571},
{"learn":[0.2208657257],"iteration":74,"passed_time":1.459156458,"remaining_time":17.99626299},
{"learn":[0.2198043371],"iteration":75,"passed_time":1.475929333,"remaining_time":17.94419347},
{"learn":[0.2181799557],"iteration":76,"passed_time":1.497892417,"remaining_time":17.95525585},
{"learn":[0.2171065083],"iteration":77,"passed_time":1.518649667,"remaining_time":17.95121785},
{"learn":[0.2160457442],"iteration":78,"passed_time":1.537276417,"remaining_time":17.92191873},
{"learn":[0.2145103991],"iteration":79,"passed_time":1.559437625,"remaining_time":17.93353269},
{"learn":[0.2130447504],"iteration":80,"passed_time":1.577847792,"remaining_time":17.90175457},
{"learn":[0.2115697139],"iteration":81,"passed_time":1.599324292,"remaining_time":17.90463048},
{"learn":[0.2102876406],"iteration":82,"passed_time":1.621493167,"remaining_time":17.91456908},
{"learn":[0.2092963567],"iteration":83,"passed_time":1.641882208,"remaining_time":17.90433456},
{"learn":[0.2083601567],"iteration":84,"passed_time":1.662347125,"remaining_time":17.89467787},
{"learn":[0.207724381],"iteration":85,"passed_time":1.679348583,"remaining_time":17.84796053},
{"learn":[0.2065086762],"iteration":86,"passed_time":1.698187458,"remaining_time":17.82120861},
{"learn":[0.2054811298],"iteration":87,"passed_time":1.717930417,"remaining_time":17.80400614},
{"learn":[0.2041960595],"iteration":88,"passed_time":1.737380417,"remaining_time":17.78374786},
{"learn":[0.2033016205],"iteration":89,"passed_time":1.754706458,"remaining_time":17.74203197},
{"learn":[0.2021631766],"iteration":90,"passed_time":1.776339792,"remaining_time":17.7438777},
{"learn":[0.2016985755],"iteration":91,"passed_time":1.792623,"remaining_time":17.69240961},
{"learn":[0.2006278087],"iteration":92,"passed_time":1.809559208,"remaining_time":17.64806669},
{"learn":[0.1994483311],"iteration":93,"passed_time":1.825777542,"remaining_time":17.5973878},
{"learn":[0.1983840498],"iteration":94,"passed_time":1.845702333,"remaining_time":17.58274328},
{"learn":[0.1976671551],"iteration":95,"passed_time":1.862891,"remaining_time":17.54222358},
{"learn":[0.1968880532],"iteration":96,"passed_time":1.882753708,"remaining_time":17.52707834},
{"learn":[0.1955855888],"iteration":97,"passed_time":1.901386583,"remaining_time":17.50051733},
{"learn":[0.1944437383],"iteration":98,"passed_time":1.925277833,"remaining_time":17.52197301},
{"learn":[0.1928966656],"iteration":99,"passed_time":1.946136333,"remaining_time":17.515227},
{"learn":[0.1918469823],"iteration":100,"passed_time":1.964064083,"remaining_time":17.48211496},
{"learn":[0.1902895564],"iteration":101,"passed_time":1.984192292,"remaining_time":17.46867331},
{"learn":[0.1886565588],"iteration":102,"passed_time":2.007390625,"remaining_time":17.48183874},
{"learn":[0.1879220443],"iteration":103,"passed_time":2.024358875,"remaining_time":17.44063031},
{"learn":[0.186234052],"iteration":104,"passed_time":2.048281583,"remaining_time":17.45916207},
{"learn":[0.1845308643],"iteration":105,"passed_time":2.073429625,"remaining_time":17.48722721},
{"learn":[0.1836469001],"iteration":106,"passed_time":2.09182675,"remaining_time":17.45795596},
{"learn":[0.1818480426],"iteration":107,"passed_time":2.114010833,"remaining_time":17.46016355},
{"learn":[0.1803072897],"iteration":108,"passed_time":2.140730625,"remaining_time":17.49899988},
{"learn":[0.1790656101],"iteration":109,"passed_time":2.16177875,"remaining_time":17.49075534},
{"learn":[0.1778968734],"iteration":110,"passed_time":2.182134375,"remaining_time":17.47673387},
{"learn":[0.1766275146],"iteration":111,"passed_time":2.209882792,"remaining_time":17.52121356},
{"learn":[0.1746281844],"iteration":112,"passed_time":2.239517208,"remaining_time":17.57921915},
{"learn":[0.1733874985],"iteration":113,"passed_time":2.25995575,"remaining_time":17.5642175},
{"learn":[0.1718242171],"iteration":114,"passed_time":2.285662292,"remaining_time":17.58966198},
{"learn":[0.1702876556],"iteration":115,"passed_time":2.310551542,"remaining_time":17.60799623},
{"learn":[0.168027264],"iteration":116,"passed_time":2.338534833,"remaining_time":17.64894237},
{"learn":[0.1659136604],"iteration":117,"passed_time":2.365091708,"remaining_time":17.67805836},
{"learn":[0.163504498],"iteration":118,"passed_time":2.3918725,"remaining_time":17.70789641},
{"learn":[0.1617120516],"iteration":119,"passed_time":2.418223833,"remaining_time":17.73364144},
{"learn":[0.1604885199],"iteration":120,"passed_time":2.441812792,"remaining_time":17.73845821},
{"learn":[0.1590342356],"iteration":121,"passed_time":2.468209167,"remaining_time":17.76301351},
{"learn":[0.1572810221],"iteration":122,"passed_time":2.496105667,"remaining_time":17.79743634},
{"learn":[0.155644665],"iteration":123,"passed_time":2.523802667,"remaining_time":17.82944465},
{"learn":[0.1533572163],"iteration":124,"passed_time":2.549862917,"remaining_time":17.84904042},
{"learn":[0.1514232491],"iteration":125,"passed_time":2.575139458,"remaining_time":17.86247529},
{"learn":[0.1495051798],"iteration":126,"passed_time":2.604276792,"remaining_time":17.90183968},
{"learn":[0.1476003152],"iteration":127,"passed_time":2.634672833,"remaining_time":17.94870868},
{"learn":[0.1455910509],"iteration":128,"passed_time":2.661160375,"remaining_time":17.96798982},
{"learn":[0.143781433],"iteration":129,"passed_time":2.690034583,"remaining_time":18.00253913},
{"learn":[0.1420383358],"iteration":130,"passed_time":2.715309292,"remaining_time":18.01224255},
{"learn":[0.140866547],"iteration":131,"passed_time":2.7406415,"remaining_time":18.02179411},
{"learn":[0.1390167822],"iteration":132,"passed_time":2.769818542,"remaining_time":18.05588478},
{"learn":[0.137415357],"iteration":133,"passed_time":2.802154,"remaining_time":18.10944301},
{"learn":[0.1358557424],"iteration":134,"passed_time":2.829883958,"remaining_time":18.13221944},
{"learn":[0.1342826184],"iteration":135,"passed_time":2.860115375,"remaining_time":18.17014474},
{"learn":[0.1333532615],"iteration":136,"passed_time":2.88409725,"remaining_time":18.16770749},
{"learn":[0.1322883394],"iteration":137,"passed_time":2.907764833,"remaining_time":18.16299483},
{"learn":[0.1305481624],"iteration":138,"passed_time":2.937356958,"remaining_time":18.19470749},
{"learn":[0.1289832175],"iteration":139,"passed_time":2.966594625,"remaining_time":18.22336698},
{"learn":[0.1276733948],"iteration":140,"passed_time":2.995311792,"remaining_time":18.24803425},
{"learn":[0.1260640625],"iteration":141,"passed_time":3.021235167,"remaining_time":18.25506882},
{"learn":[0.1242763168],"iteration":142,"passed_time":3.052119875,"remaining_time":18.29137575},
{"learn":[0.1225788358],"iteration":143,"passed_time":3.080524917,"remaining_time":18.31200923},
{"learn":[0.1211115518],"iteration":144,"passed_time":3.111094333,"remaining_time":18.34472866},
{"learn":[0.120119324],"iteration":145,"passed_time":3.137902,"remaining_time":18.35457745},
{"learn":[0.119030858],"iteration":146,"passed_time":3.166516708,"remaining_time":18.37441328},
{"learn":[0.1178464987],"iteration":147,"passed_time":3.195238708,"remaining_time":18.39421202},
{"learn":[0.1163878618],"iteration":148,"passed_time":3.226544708,"remaining_time":18.42811776},
{"learn":[0.1148503939],"iteration":149,"passed_time":3.255386833,"remaining_time":18.44719206},
{"learn":[0.1138482108],"iteration":150,"passed_time":3.281308625,"remaining_time":18.44921207},
{"learn":[0.1129948903],"iteration":151,"passed_time":3.305932708,"remaining_time":18.44362458},
{"learn":[0.1117758945],"iteration":152,"passed_time":3.333936583,"remaining_time":18.4564986},
{"learn":[0.1106493509],"iteration":153,"passed_time":3.36525725,"remaining_time":18.48706256},
{"learn":[0.1095231351],"iteration":154,"passed_time":3.395551542,"remaining_time":18.5112326},
{"learn":[0.1087118273],"iteration":155,"passed_time":3.423312083,"remaining_time":18.52099614},
{"learn":[0.1071637352],"iteration":156,"passed_time":3.454594542,"remaining_time":18.54919235},
{"learn":[0.106187874],"iteration":157,"passed_time":3.479838833,"remaining_time":18.54445758},
{"learn":[0.1048152881],"iteration":158,"passed_time":3.511180125,"remaining_time":18.57171374},
{"learn":[0.1038341394],"iteration":159,"passed_time":3.539364417,"remaining_time":18.58166319},
{"learn":[0.1026989503],"iteration":160,"passed_time":3.570163167,"remaining_time":18.60476333},
{"learn":[0.1015024959],"iteration":161,"passed_time":3.6023745,"remaining_time":18.63450513},
{"learn":[0.1006971447],"iteration":162,"passed_time":3.630879292,"remaining_time":18.64445379},
{"learn":[0.1000847465],"iteration":163,"passed_time":3.658305917,"remaining_time":18.64843748},
{"learn":[0.09914456289],"iteration":164,"passed_time":3.684416375,"remaining_time":18.64537984},
{"learn":[0.0980666922],"iteration":165,"passed_time":3.715788792,"remaining_time":18.66848104},
{"learn":[0.097059219],"iteration":166,"passed_time":3.7444235,"remaining_time":18.6772741},
{"learn":[0.09599812135],"iteration":167,"passed_time":3.774002583,"remaining_time":18.69029851},
{"learn":[0.09529148764],"iteration":168,"passed_time":3.80224225,"remaining_time":18.6962326},
{"learn":[0.09472885217],"iteration":169,"passed_time":3.830910833,"remaining_time":18.70385877},
{"learn":[0.09399239641],"iteration":170,"passed_time":3.8579455,"remaining_time":18.7031393},
{"learn":[0.09298109652],"iteration":171,"passed_time":3.886879958,"remaining_time":18.71125933},
{"learn":[0.09221974409],"iteration":172,"passed_time":3.917546167,"remaining_time":18.72722936},
{"learn":[0.09125789873],"iteration":173,"passed_time":3.945266458,"remaining_time":18.7286787},
{"learn":[0.09032094466],"iteration":174,"passed_time":3.9776545,"remaining_time":18.75179979},
{"learn":[0.08925187711],"iteration":175,"passed_time":4.008042167,"remaining_time":18.76492469},
{"learn":[0.08811812269],"iteration":176,"passed_time":4.041078125,"remaining_time":18.78987173},
{"learn":[0.08733878452],"iteration":177,"passed_time":4.070022917,"remaining_time":18.79527437},
{"learn":[0.08627157876],"iteration":178,"passed_time":4.103859417,"remaining_time":18.8227295},
{"learn":[0.08531367981],"iteration":179,"passed_time":4.133237042,"remaining_time":18.82919097},
{"learn":[0.08448155169],"iteration":180,"passed_time":4.164766333,"remaining_time":18.84499241},
{"learn":[0.0835672218],"iteration":181,"passed_time":4.194708083,"remaining_time":18.85313853},
{"learn":[0.08267881235],"iteration":182,"passed_time":4.228572583,"remaining_time":18.87838142},
{"learn":[0.08193847576],"iteration":183,"passed_time":4.257166875,"remaining_time":18.87960962},
{"learn":[0.08154483259],"iteration":184,"passed_time":4.28349925,"remaining_time":18.87055075},
{"learn":[0.08045379571],"iteration":185,"passed_time":4.314865333,"remaining_time":18.88333538},
{"learn":[0.07946763434],"iteration":186,"passed_time":4.347549583,"remaining_time":18.90137867},
{"learn":[0.07855790609],"iteration":187,"passed_time":4.379685708,"remaining_time":18.91651487},
{"learn":[0.07789254275],"iteration":188,"passed_time":4.409808167,"remaining_time":18.92251018},
{"learn":[0.07707996528],"iteration":189,"passed_time":4.442474375,"remaining_time":18.9389697},
{"learn":[0.07655016424],"iteration":190,"passed_time":4.471273792,"remaining_time":18.93853664},
{"learn":[0.07601748451],"iteration":191,"passed_time":4.50072825,"remaining_time":18.94056472},
{"learn":[0.07544150723],"iteration":192,"passed_time":4.530027417,"remaining_time":18.94161723},
{"learn":[0.07487122779],"iteration":193,"passed_time":4.55973125,"remaining_time":18.94403808},
{"learn":[0.07428754595],"iteration":194,"passed_time":4.588855625,"remaining_time":18.94373732},
{"learn":[0.07371724198],"iteration":195,"passed_time":4.615171042,"remaining_time":18.93161999},
{"learn":[0.0731672052],"iteration":196,"passed_time":4.644592125,"remaining_time":18.93201765},
{"learn":[0.07255406584],"iteration":197,"passed_time":4.675818625,"remaining_time":18.93942696},
{"learn":[0.0720986633],"iteration":198,"passed_time":4.700213625,"remaining_time":18.91895032},
{"learn":[0.0713287096],"iteration":199,"passed_time":4.729534375,"remaining_time":18.9181375},
{"learn":[0.0705599203],"iteration":200,"passed_time":4.755627042,"remaining_time":18.90420899},
{"learn":[0.06984048994],"iteration":201,"passed_time":4.78515075,"remaining_time":18.90371435},
{"learn":[0.06929370734],"iteration":202,"passed_time":4.811907667,"remaining_time":18.89207099},
{"learn":[0.06887538103],"iteration":203,"passed_time":4.838190375,"remaining_time":18.87842911},
{"learn":[0.0682432284],"iteration":204,"passed_time":4.870450208,"remaining_time":18.88784349},
{"learn":[0.0676518515],"iteration":205,"passed_time":4.900076917,"remaining_time":18.88670423},
{"learn":[0.06682273244],"iteration":206,"passed_time":4.931521417,"remaining_time":18.89225354},
{"learn":[0.06623689832],"iteration":207,"passed_time":4.959696375,"remaining_time":18.88499774},
{"learn":[0.06568260125],"iteration":208,"passed_time":4.992046917,"remaining_time":18.89334503},
{"learn":[0.06517997315],"iteration":209,"passed_time":5.022117375,"remaining_time":18.89272727},
{"learn":[0.06469075908],"iteration":210,"passed_time":5.049976167,"remaining_time":18.88356017},
{"learn":[0.06436581873],"iteration":211,"passed_time":5.077362333,"remaining_time":18.87245999},
{"learn":[0.06377904194],"iteration":212,"passed_time":5.110588583,"remaining_time":18.88278505},
{"learn":[0.06324374644],"iteration":213,"passed_time":5.14538425,"remaining_time":18.89846739},
{"learn":[0.06300620801],"iteration":214,"passed_time":5.1673735,"remaining_time":18.86692185},
{"learn":[0.06252936537],"iteration":215,"passed_time":5.195377792,"remaining_time":18.85729717},
{"learn":[0.062058173],"iteration":216,"passed_time":5.22505375,"remaining_time":18.85353496},
{"learn":[0.06158054875],"iteration":217,"passed_time":5.255967667,"remaining_time":18.85397576},
{"learn":[0.06080924204],"iteration":218,"passed_time":5.290328125,"remaining_time":18.8664213},
{"learn":[0.06013530147],"iteration":219,"passed_time":5.32401975,"remaining_time":18.87607002},
{"learn":[0.05959300309],"iteration":220,"passed_time":5.354543125,"remaining_time":18.8741588},
{"learn":[0.05899316352],"iteration":221,"passed_time":5.387139958,"remaining_time":18.87925625},
{"learn":[0.05865019223],"iteration":222,"passed_time":5.421043792,"remaining_time":18.88856962},
{"learn":[0.05813167261],"iteration":223,"passed_time":5.45122175,"remaining_time":18.88458963},
{"learn":[0.05743669574],"iteration":224,"passed_time":5.481105458,"remaining_time":18.87936325},
{"learn":[0.05704546193],"iteration":225,"passed_time":5.511316167,"remaining_time":18.87503855},
{"learn":[0.05655932088],"iteration":226,"passed_time":5.543476125,"remaining_time":18.87712354},
{"learn":[0.05597996313],"iteration":227,"passed_time":5.576498583,"remaining_time":18.88182854},
{"learn":[0.05551924921],"iteration":228,"passed_time":5.606499417,"remaining_time":18.87603079},
{"learn":[0.05507864029],"iteration":229,"passed_time":5.634334458,"remaining_time":18.86277188},
{"learn":[0.05462053399],"iteration":230,"passed_time":5.666090958,"remaining_time":18.86244133},
{"learn":[0.05411380974],"iteration":231,"passed_time":5.699407417,"remaining_time":18.86700386},
{"learn":[0.05371225248],"iteration":232,"passed_time":5.727856792,"remaining_time":18.85521957},
{"learn":[0.05329201511],"iteration":233,"passed_time":5.758960958,"remaining_time":18.85198331},
{"learn":[0.05295001437],"iteration":234,"passed_time":5.786949208,"remaining_time":18.83836657},
{"learn":[0.05258441603],"iteration":235,"passed_time":5.815678292,"remaining_time":18.82702633},
{"learn":[0.05225470835],"iteration":236,"passed_time":5.84479625,"remaining_time":18.8167913},
{"learn":[0.05184690812],"iteration":237,"passed_time":5.878204583,"remaining_time":18.820134},
{"learn":[0.05146368829],"iteration":238,"passed_time":5.906376833,"remaining_time":18.80649695},
{"learn":[0.05095861874],"iteration":239,"passed_time":5.939316417,"remaining_time":18.80783532},
{"learn":[0.05057472202],"iteration":240,"passed_time":5.968038,"remaining_time":18.79560515},
{"learn":[0.05021863943],"iteration":241,"passed_time":6.00139475,"remaining_time":18.79775711},
{"learn":[0.04984517074],"iteration":242,"passed_time":6.03171075,"remaining_time":18.79014419},
{"learn":[0.04938549622],"iteration":243,"passed_time":6.063713458,"remaining_time":18.78757121},
{"learn":[0.04907727749],"iteration":244,"passed_time":6.092203958,"remaining_time":18.77393465},
{"learn":[0.04856165663],"iteration":245,"passed_time":6.125945375,"remaining_time":18.7762716},
{"learn":[0.04824294218],"iteration":246,"passed_time":6.155645292,"remaining_time":18.76599557},
{"learn":[0.04788890866],"iteration":247,"passed_time":6.18957725,"remaining_time":18.76839553},
{"learn":[0.04754939816],"iteration":248,"passed_time":6.221670833,"remaining_time":18.76495902},
{"learn":[0.04723941904],"iteration":249,"passed_time":6.251024,"remaining_time":18.753072},
{"learn":[0.04681194668],"iteration":250,"passed_time":6.284061292,"remaining_time":18.75203947},
{"learn":[0.04649590437],"iteration":251,"passed_time":6.315190333,"remaining_time":18.74508877},
{"learn":[0.04631194896],"iteration":252,"passed_time":6.340621583,"remaining_time":18.72112381},
{"learn":[0.04607508105],"iteration":253,"passed_time":6.369975583,"remaining_time":18.70866845},
{"learn":[0.04572436462],"iteration":254,"passed_time":6.402084625,"remaining_time":18.70412959},
{"learn":[0.04532661652],"iteration":255,"passed_time":6.434653583,"remaining_time":18.70071198},
{"learn":[0.04495931661],"iteration":256,"passed_time":6.465909333,"remaining_time":18.69327095},
{"learn":[0.04467234563],"iteration":257,"passed_time":6.495382125,"remaining_time":18.68051758},
{"learn":[0.04432105299],"iteration":258,"passed_time":6.529081667,"remaining_time":18.67972786},
{"learn":[0.04404945658],"iteration":259,"passed_time":6.558835417,"remaining_time":18.66745465},
{"learn":[0.04366678319],"iteration":260,"passed_time":6.592668667,"remaining_time":18.66659826},
{"learn":[0.04341409368],"iteration":261,"passed_time":6.621346708,"remaining_time":18.65096897},
{"learn":[0.04313002912],"iteration":262,"passed_time":6.650686667,"remaining_time":18.63709534},
{"learn":[0.04275380774],"iteration":263,"passed_time":6.682902167,"remaining_time":18.63112119},
{"learn":[0.04253611866],"iteration":264,"passed_time":6.711075667,"remaining_time":18.61373817},
{"learn":[0.04223534877],"iteration":265,"passed_time":6.740997417,"remaining_time":18.60109813},
{"learn":[0.04176678274],"iteration":266,"passed_time":6.77696325,"remaining_time":18.60492158},
{"learn":[0.04150711431],"iteration":267,"passed_time":6.806188958,"remaining_time":18.5900385},
{"learn":[0.04124586947],"iteration":268,"passed_time":6.83646,"remaining_time":18.57788944},
{"learn":[0.04090178687],"iteration":269,"passed_time":6.864354708,"remaining_time":18.55918125},
{"learn":[0.04066961499],"iteration":270,"passed_time":6.893360292,"remaining_time":18.54339355},
{"learn":[0.04026719562],"iteration":271,"passed_time":6.928152542,"remaining_time":18.54299651},
{"learn":[0.03997523374],"iteration":272,"passed_time":6.959390167,"remaining_time":18.53288151},
{"learn":[0.03969386175],"iteration":273,"passed_time":6.9914455,"remaining_time":18.52477895},
{"learn":[0.03946002333],"iteration":274,"passed_time":7.022987,"remaining_time":18.51514755},
{"learn":[0.03915533849],"iteration":275,"passed_time":7.05719275,"remaining_time":18.5123462},
{"learn":[0.03885332582],"iteration":276,"passed_time":7.087950958,"remaining_time":18.50031965},
{"learn":[0.03868180348],"iteration":277,"passed_time":7.113791833,"remaining_time":18.47538742},
{"learn":[0.03851615746],"iteration":278,"passed_time":7.141837125,"remaining_time":18.4561454},
{"learn":[0.03823699293],"iteration":279,"passed_time":7.17481975,"remaining_time":18.4495365},
{"learn":[0.03790104915],"iteration":280,"passed_time":7.207441,"remaining_time":18.44181523},
{"learn":[0.03770177389],"iteration":281,"passed_time":7.244649792,"remaining_time":18.4455977},
{"learn":[0.03750521511],"iteration":282,"passed_time":7.274950333,"remaining_time":18.43158795},
{"learn":[0.03730280693],"iteration":283,"passed_time":7.303276,"remaining_time":18.41248456},
{"learn":[0.0369723487],"iteration":284,"passed_time":7.333455208,"remaining_time":18.39796658},
{"learn":[0.03676396125],"iteration":285,"passed_time":7.362300042,"remaining_time":18.3800078},
{"learn":[0.03649757139],"iteration":286,"passed_time":7.391867375,"remaining_time":18.36376808},
{"learn":[0.03627870999],"iteration":287,"passed_time":7.421279,"remaining_time":18.34705086},
{"learn":[0.03605078822],"iteration":288,"passed_time":7.45082125,"remaining_time":18.33056716},
{"learn":[0.035883239],"iteration":289,"passed_time":7.479737,"remaining_time":18.31245955},
{"learn":[0.03559742316],"iteration":290,"passed_time":7.509372,"remaining_time":18.29603006},
{"learn":[0.03530275735],"iteration":291,"passed_time":7.5407725,"remaining_time":18.28379086},
{"learn":[0.03501364971],"iteration":292,"passed_time":7.570936917,"remaining_time":18.26843823},
{"learn":[0.03479913936],"iteration":293,"passed_time":7.599602708,"remaining_time":18.2493861},
{"learn":[0.03455634976],"iteration":294,"passed_time":7.627728625,"remaining_time":18.22897858},
{"learn":[0.03435611997],"iteration":295,"passed_time":7.655547833,"remaining_time":18.20778944},
{"learn":[0.03417069938],"iteration":296,"passed_time":7.682832875,"remaining_time":18.18529128},
{"learn":[0.03383213646],"iteration":297,"passed_time":7.711706625,"remaining_time":18.16650353},
{"learn":[0.03361413861],"iteration":298,"passed_time":7.738899875,"remaining_time":18.1437084},
{"learn":[0.03339574098],"iteration":299,"passed_time":7.765842833,"remaining_time":18.12029994},
{"learn":[0.03325179708],"iteration":300,"passed_time":7.794504417,"remaining_time":18.10085909},
{"learn":[0.03304489299],"iteration":301,"passed_time":7.820207875,"remaining_time":18.07452019},
{"learn":[0.03277837619],"iteration":302,"passed_time":7.84835275,"remaining_time":18.05380154},
{"learn":[0.0325527362],"iteration":303,"passed_time":7.875444,"remaining_time":18.03062179},
{"learn":[0.0322429964],"iteration":304,"passed_time":7.905267792,"remaining_time":18.013643},
{"learn":[0.03210026207],"iteration":305,"passed_time":7.930010208,"remaining_time":17.98505583},
{"learn":[0.03194376435],"iteration":306,"passed_time":7.955446375,"remaining_time":17.95805973},
{"learn":[0.03184627979],"iteration":307,"passed_time":7.976101875,"remaining_time":17.92033278},
{"learn":[0.03161358683],"iteration":308,"passed_time":8.00506375,"remaining_time":17.90129143},
{"learn":[0.03146437688],"iteration":309,"passed_time":8.029909208,"remaining_time":17.87302372},
{"learn":[0.03122513196],"iteration":310,"passed_time":8.060030208,"remaining_time":17.85646564},
{"learn":[0.03103119193],"iteration":311,"passed_time":8.089107417,"remaining_time":17.83751892},
{"learn":[0.03078154787],"iteration":312,"passed_time":8.118851792,"remaining_time":17.81997182},
{"learn":[0.03055492031],"iteration":313,"passed_time":8.148588292,"remaining_time":17.80232983},
{"learn":[0.03045727499],"iteration":314,"passed_time":8.173411167,"remaining_time":17.77392587},
{"learn":[0.0303080988],"iteration":315,"passed_time":8.204926292,"remaining_time":17.76003033},
{"learn":[0.03015919536],"iteration":316,"passed_time":8.236864708,"remaining_time":17.74693563},
{"learn":[0.02995863269],"iteration":317,"passed_time":8.267483833,"remaining_time":17.730893},
{"learn":[0.0298137834],"iteration":318,"passed_time":8.2974975,"remaining_time":17.71346645},
{"learn":[0.02964808149],"iteration":319,"passed_time":8.325482875,"remaining_time":17.69165111},
{"learn":[0.02946340963],"iteration":320,"passed_time":8.353674083,"remaining_time":17.67023272},
{"learn":[0.029347444],"iteration":321,"passed_time":8.381491042,"remaining_time":17.64798424},
{"learn":[0.02912442081],"iteration":322,"passed_time":8.410614458,"remaining_time":17.62843959},
{"learn":[0.02904449807],"iteration":323,"passed_time":8.434466083,"remaining_time":17.59783664},
{"learn":[0.02889964431],"iteration":324,"passed_time":8.45814375,"remaining_time":17.56691394},
{"learn":[0.0288231489],"iteration":325,"passed_time":8.482598292,"remaining_time":17.53764187},
{"learn":[0.02859687339],"iteration":326,"passed_time":8.513017625,"remaining_time":17.52067542},
{"learn":[0.02851524696],"iteration":327,"passed_time":8.535742,"remaining_time":17.48786166},
{"learn":[0.02836708955],"iteration":328,"passed_time":8.562698583,"remaining_time":17.46374088},
{"learn":[0.02830090944],"iteration":329,"passed_time":8.583706125,"remaining_time":17.42752456},
{"learn":[0.02817877857],"iteration":330,"passed_time":8.612763708,"remaining_time":17.40767046},
{"learn":[0.02812179922],"iteration":331,"passed_time":8.63287525,"remaining_time":17.36976105},
{"learn":[0.02798204518],"iteration":332,"passed_time":8.666042917,"remaining_time":17.35810999},
{"learn":[0.0278738664],"iteration":333,"passed_time":8.695723875,"remaining_time":17.33937755},
{"learn":[0.02777092847],"iteration":334,"passed_time":8.717443125,"remaining_time":17.30477516},
{"learn":[0.02758229315],"iteration":335,"passed_time":8.747209042,"remaining_time":17.2861512},
{"learn":[0.02744886106],"iteration":336,"passed_time":8.773049333,"remaining_time":17.25973801},
{"learn":[0.02730796406],"iteration":337,"passed_time":8.801199208,"remaining_time":17.2378517},
{"learn":[0.02712273668],"iteration":338,"passed_time":8.829627083,"remaining_time":17.21647051},
{"learn":[0.02707557856],"iteration":339,"passed_time":8.849091917,"remaining_time":17.17764901},
{"learn":[0.02695386719],"iteration":340,"passed_time":8.877295833,"remaining_time":17.15582978},
{"learn":[0.02681985924],"iteration":341,"passed_time":8.901078917,"remaining_time":17.12546762},
{"learn":[0.0266936565],"iteration":342,"passed_time":8.925221,"remaining_time":17.09583148},
{"learn":[0.02651079311],"iteration":343,"passed_time":8.954977667,"remaining_time":17.07693416},
{"learn":[0.02631062368],"iteration":344,"passed_time":8.986991875,"remaining_time":17.06225994},
{"learn":[0.02613786414],"iteration":345,"passed_time":9.018495875,"remaining_time":17.0465211},
{"learn":[0.02607144507],"iteration":346,"passed_time":9.039881,"remaining_time":17.01164926},
{"learn":[0.02593163855],"iteration":347,"passed_time":9.070841,"remaining_time":16.99479406},
{"learn":[0.02582985774],"iteration":348,"passed_time":9.095132042,"remaining_time":16.96541822},
{"learn":[0.02569740255],"iteration":349,"passed_time":9.12459975,"remaining_time":16.94568525},
{"learn":[0.02557887002],"iteration":350,"passed_time":9.151884667,"remaining_time":16.92186082},
{"learn":[0.02550033194],"iteration":351,"passed_time":9.17987275,"remaining_time":16.8993112},
{"learn":[0.02541520716],"iteration":352,"passed_time":9.208010417,"remaining_time":16.87700493},
{"learn":[0.02530607856],"iteration":353,"passed_time":9.234762667,"remaining_time":16.85213752},
{"learn":[0.02514188687],"iteration":354,"passed_time":9.267638875,"remaining_time":16.83838613},
{"learn":[0.02502933309],"iteration":355,"passed_time":9.298215167,"remaining_time":16.82036676},
{"learn":[0.02491180584],"iteration":356,"passed_time":9.323590583,"remaining_time":16.79290965},
{"learn":[0.02480098373],"iteration":357,"passed_time":9.354317625,"remaining_time":16.77506122},
{"learn":[0.02467443655],"iteration":358,"passed_time":9.384921625,"remaining_time":16.75692134},
{"learn":[0.02455470716],"iteration":359,"passed_time":9.414022167,"remaining_time":16.73603941},
{"learn":[0.02447161363],"iteration":360,"passed_time":9.438252583,"remaining_time":16.70649141},
{"learn":[0.02440364602],"iteration":361,"passed_time":9.463949083,"remaining_time":16.67955667},
{"learn":[0.02424752995],"iteration":362,"passed_time":9.493738625,"remaining_time":16.65981131},
{"learn":[0.02416922744],"iteration":363,"passed_time":9.513976792,"remaining_time":16.62332209},
{"learn":[0.02409016285],"iteration":364,"passed_time":9.544925958,"remaining_time":16.60555612},
{"learn":[0.02395261726],"iteration":365,"passed_time":9.578239875,"remaining_time":16.59181443},
{"learn":[0.02387293397],"iteration":366,"passed_time":9.604284958,"remaining_time":16.56542882},
{"learn":[0.02372855835],"iteration":367,"passed_time":9.63222725,"remaining_time":16.54230332},
{"learn":[0.02357871995],"iteration":368,"passed_time":9.664085083,"remaining_time":16.52584739},
{"learn":[0.02343148467],"iteration":369,"passed_time":9.693445667,"remaining_time":16.50505614},
{"learn":[0.02335244125],"iteration":370,"passed_time":9.716660667,"remaining_time":16.47379935},
{"learn":[0.02325647691],"iteration":371,"passed_time":9.743986292,"remaining_time":16.44952525},
{"learn":[0.02318975088],"iteration":372,"passed_time":9.766264958,"remaining_time":16.41675102},
{"learn":[0.02312865302],"iteration":373,"passed_time":9.792115542,"remaining_time":16.39001158},
{"learn":[0.02301412707],"iteration":374,"passed_time":9.817555042,"remaining_time":16.36259174},
{"learn":[0.02288630305],"iteration":375,"passed_time":9.843678458,"remaining_time":16.33631744},
{"learn":[0.0227926191],"iteration":376,"passed_time":9.871261292,"remaining_time":16.31245566},
{"learn":[0.02270476678],"iteration":377,"passed_time":9.900279833,"remaining_time":16.29093666},
{"learn":[0.02264786275],"iteration":378,"passed_time":9.924320208,"remaining_time":16.26122124},
{"learn":[0.0225109804],"iteration":379,"passed_time":9.953805792,"remaining_time":16.24041998},
{"learn":[0.02242591782],"iteration":380,"passed_time":9.980643625,"remaining_time":16.2152714},
{"learn":[0.02230300618],"iteration":381,"passed_time":10.00946425,"remaining_time":16.19332174},
{"learn":[0.02224679956],"iteration":382,"passed_time":10.03250492,"remaining_time":16.16202489},
{"learn":[0.02214484442],"iteration":383,"passed_time":10.06296167,"remaining_time":16.14266767},
{"learn":[0.02205381603],"iteration":384,"passed_time":10.09085496,"remaining_time":16.11915792},
{"learn":[0.02199432442],"iteration":385,"passed_time":10.11550988,"remaining_time":16.09047426},
{"learn":[0.02189492307],"iteration":386,"passed_time":10.143499,"remaining_time":16.06709273},
{"learn":[0.02180522262],"iteration":387,"passed_time":10.17246117,"remaining_time":16.04522225},
{"learn":[0.02174540197],"iteration":388,"passed_time":10.19404304,"remaining_time":16.01172313},
{"learn":[0.02163741344],"iteration":389,"passed_time":10.22303383,"remaining_time":15.98987343},
{"learn":[0.02156958115],"iteration":390,"passed_time":10.25007917,"remaining_time":15.96495707},
{"learn":[0.0214905602],"iteration":391,"passed_time":10.27399183,"remaining_time":15.93517101},
{"learn":[0.02144718206],"iteration":392,"passed_time":10.29721208,"remaining_time":15.90434538},
{"learn":[0.02134352723],"iteration":393,"passed_time":10.324702,"remaining_time":15.88012541},
{"learn":[0.0212733959],"iteration":394,"passed_time":10.3505135,"remaining_time":15.85331815},
{"learn":[0.02116905541],"iteration":395,"passed_time":10.37999383,"remaining_time":15.83211181},
{"learn":[0.02113966547],"iteration":396,"passed_time":10.39986213,"remaining_time":15.79626413},
{"learn":[0.0210662694],"iteration":397,"passed_time":10.42402404,"remaining_time":15.76699114},
{"learn":[0.0209931259],"iteration":398,"passed_time":10.45164021,"remaining_time":15.74294678},
{"learn":[0.02090175076],"iteration":399,"passed_time":10.47870067,"remaining_time":15.718051},
{"learn":[0.02084842048],"iteration":400,"passed_time":10.50490279,"remaining_time":15.69186227},
{"learn":[0.02078149105],"iteration":401,"passed_time":10.53359338,"remaining_time":15.66937522},
{"learn":[0.02066456589],"iteration":402,"passed_time":10.56472558,"remaining_time":15.65047438},
{"learn":[0.02058825238],"iteration":403,"passed_time":10.59526817,"remaining_time":15.63064314},
{"learn":[0.02054971703],"iteration":404,"passed_time":10.61995954,"remaining_time":15.60216278},
{"learn":[0.02047480281],"iteration":405,"passed_time":10.6473665,"remaining_time":15.57767414},
{"learn":[0.02039416883],"iteration":406,"passed_time":10.67705263,"remaining_time":15.55649191},
{"learn":[0.02033005713],"iteration":407,"passed_time":10.70436754,"remaining_time":15.53182741},
{"learn":[0.02030079246],"iteration":408,"passed_time":10.72622633,"remaining_time":15.49926592},
{"learn":[0.02024340352],"iteration":409,"passed_time":10.75462829,"remaining_time":15.47617242},
{"learn":[0.02020099516],"iteration":410,"passed_time":10.77460779,"remaining_time":15.44098294},
{"learn":[0.02009033738],"iteration":411,"passed_time":10.80636721,"remaining_time":15.42267941},
{"learn":[0.02002932143],"iteration":412,"passed_time":10.83271879,"remaining_time":15.39662453},
{"learn":[0.01997218609],"iteration":413,"passed_time":10.86005583,"remaining_time":15.37196309},
{"learn":[0.01990245697],"iteration":414,"passed_time":10.88516733,"remaining_time":15.34415154},
{"learn":[0.01981667867],"iteration":415,"passed_time":10.91431883,"remaining_time":15.32202452},
{"learn":[0.01974422281],"iteration":416,"passed_time":10.94176438,"remaining_time":15.29747873},
{"learn":[0.01970528659],"iteration":417,"passed_time":10.96733571,"remaining_time":15.27030953},
{"learn":[0.01964618693],"iteration":418,"passed_time":10.99392992,"remaining_time":15.2445663},
{"learn":[0.0195586008],"iteration":419,"passed_time":11.02415046,"remaining_time":15.22382682},
{"learn":[0.01947835084],"iteration":420,"passed_time":11.05496767,"remaining_time":15.2038629},
{"learn":[0.0194062865],"iteration":421,"passed_time":11.08933413,"remaining_time":15.18870883},
{"learn":[0.01938745992],"iteration":422,"passed_time":11.11334179,"remaining_time":15.15933384},
{"learn":[0.0193448501],"iteration":423,"passed_time":11.13656829,"remaining_time":15.12892296},
{"learn":[0.01929857923],"iteration":424,"passed_time":11.16333704,"remaining_time":15.10333835},
{"learn":[0.01925162064],"iteration":425,"passed_time":11.18916408,"remaining_time":15.0764793},
{"learn":[0.01917526332],"iteration":426,"passed_time":11.21792683,"remaining_time":15.05356458},
{"learn":[0.01910339715],"iteration":427,"passed_time":11.24785658,"remaining_time":15.03218216},
{"learn":[0.01903182985],"iteration":428,"passed_time":11.27646521,"remaining_time":15.00900148},
{"learn":[0.01895298369],"iteration":429,"passed_time":11.30508663,"remaining_time":14.9858125},
{"learn":[0.01889522953],"iteration":430,"passed_time":11.33028183,"remaining_time":14.95807509},
{"learn":[0.01879608214],"iteration":431,"passed_time":11.36009604,"remaining_time":14.93642257},
{"learn":[0.01874095791],"iteration":432,"passed_time":11.38314517,"remaining_time":14.90587369},
{"learn":[0.01866630733],"iteration":433,"passed_time":11.41105688,"remaining_time":14.8817009},
{"learn":[0.01862831169],"iteration":434,"passed_time":11.43816854,"remaining_time":14.85647178},
{"learn":[0.01854960489],"iteration":435,"passed_time":11.46683767,"remaining_time":14.83324872},
{"learn":[0.01846379642],"iteration":436,"passed_time":11.49756354,"remaining_time":14.81265051},
{"learn":[0.01839884413],"iteration":437,"passed_time":11.52328458,"remaining_time":14.78558433},
{"learn":[0.01832837725],"iteration":438,"passed_time":11.55358708,"remaining_time":14.76437894},
{"learn":[0.01829124365],"iteration":439,"passed_time":11.579459,"remaining_time":14.73749327},
{"learn":[0.01826985646],"iteration":440,"passed_time":11.60402263,"remaining_time":14.70895385},
{"learn":[0.01820955509],"iteration":441,"passed_time":11.627062,"remaining_time":14.67850814},
{"learn":[0.01817733584],"iteration":442,"passed_time":11.64800733,"remaining_time":14.64546295},
{"learn":[0.01815483736],"iteration":443,"passed_time":11.67339017,"remaining_time":14.61802913},
{"learn":[0.01807968228],"iteration":444,"passed_time":11.70589708,"remaining_time":14.59948962},
{"learn":[0.01798814604],"iteration":445,"passed_time":11.73497675,"remaining_time":14.57663031},
{"learn":[0.01793268542],"iteration":446,"passed_time":11.76091525,"remaining_time":14.54985712},
{"learn":[0.01788407134],"iteration":447,"passed_time":11.78648354,"remaining_time":14.52263151},
{"learn":[0.01784648563],"iteration":448,"passed_time":11.81268563,"remaining_time":14.49619105},
{"learn":[0.01780576361],"iteration":449,"passed_time":11.83799375,"remaining_time":14.46865903},
{"learn":[0.01775782493],"iteration":450,"passed_time":11.86092883,"remaining_time":14.43824818},
{"learn":[0.01772273555],"iteration":451,"passed_time":11.87865888,"remaining_time":14.40155988},
{"learn":[0.01764908871],"iteration":452,"passed_time":11.90614088,"remaining_time":14.37673081},
{"learn":[0.01759341165],"iteration":453,"passed_time":11.93640321,"remaining_time":14.35523381},
{"learn":[0.01755892561],"iteration":454,"passed_time":11.96226808,"remaining_time":14.328431},
{"learn":[0.01748803689],"iteration":455,"passed_time":11.99144838,"remaining_time":14.30558754},
{"learn":[0.01745184141],"iteration":456,"passed_time":12.01503096,"remaining_time":14.27606523},
{"learn":[0.01742326953],"iteration":457,"passed_time":12.0392595,"remaining_time":14.24733329},
{"learn":[0.01739406777],"iteration":458,"passed_time":12.06275879,"remaining_time":14.21776145},
{"learn":[0.01733917083],"iteration":459,"passed_time":12.09004804,"remaining_time":14.19266509},
{"learn":[0.01726573089],"iteration":460,"passed_time":12.11896417,"remaining_time":14.16946136},
{"learn":[0.01721192803],"iteration":461,"passed_time":12.14530488,"remaining_time":14.14323382},
{"learn":[0.01715391902],"iteration":462,"passed_time":12.16816804,"remaining_time":14.11297244},
{"learn":[0.01712540699],"iteration":463,"passed_time":12.18730467,"remaining_time":14.07843815},
{"learn":[0.01708225787],"iteration":464,"passed_time":12.21208121,"remaining_time":14.05045902},
{"learn":[0.01701953179],"iteration":465,"passed_time":12.23995629,"remaining_time":14.02604433},
{"learn":[0.01696343444],"iteration":466,"passed_time":12.27231542,"remaining_time":14.00673258},
{"learn":[0.01692418261],"iteration":467,"passed_time":12.30042979,"remaining_time":13.98253985},
{"learn":[0.01686818234],"iteration":468,"passed_time":12.33294479,"remaining_time":13.96331276},
{"learn":[0.01684352917],"iteration":469,"passed_time":12.35419104,"remaining_time":13.93132181},
{"learn":[0.01682227829],"iteration":470,"passed_time":12.37676679,"remaining_time":13.90086971},
{"learn":[0.01679337886],"iteration":471,"passed_time":12.40273858,"remaining_time":13.87424994},
{"learn":[0.01670579355],"iteration":472,"passed_time":12.43315688,"remaining_time":13.85258705},
{"learn":[0.01665245029],"iteration":473,"passed_time":12.459479,"remaining_time":13.82634168},
{"learn":[0.0165926542],"iteration":474,"passed_time":12.4870045,"remaining_time":13.80142603},
{"learn":[0.01654591731],"iteration":475,"passed_time":12.51870871,"remaining_time":13.7810995},
{"learn":[0.01651173273],"iteration":476,"passed_time":12.54716283,"remaining_time":13.75716176},
{"learn":[0.01647088085],"iteration":477,"passed_time":12.56779104,"remaining_time":13.72465884},
{"learn":[0.01642062846],"iteration":478,"passed_time":12.59713783,"remaining_time":13.70168854},
{"learn":[0.0163854164],"iteration":479,"passed_time":12.62560592,"remaining_time":13.67773974},
{"learn":[0.01628004388],"iteration":480,"passed_time":12.65667579,"remaining_time":13.65657949},
{"learn":[0.0162368217],"iteration":481,"passed_time":12.68529938,"remaining_time":13.63274912},
{"learn":[0.01620754544],"iteration":482,"passed_time":12.71189133,"remaining_time":13.60672426},
{"learn":[0.01616917214],"iteration":483,"passed_time":12.73886192,"remaining_time":13.58110072},
{"learn":[0.01612089868],"iteration":484,"passed_time":12.76589363,"remaining_time":13.55553653},
{"learn":[0.01609090834],"iteration":485,"passed_time":12.78499217,"remaining_time":13.52157608},
{"learn":[0.01603873573],"iteration":486,"passed_time":12.80750112,"remaining_time":13.49126915},
{"learn":[0.01600306149],"iteration":487,"passed_time":12.83364142,"remaining_time":13.46480411},
{"learn":[0.01598756951],"iteration":488,"passed_time":12.85332417,"remaining_time":13.43159233},
{"learn":[0.01594382555],"iteration":489,"passed_time":12.88070308,"remaining_time":13.40644607},
{"learn":[0.01591743883],"iteration":490,"passed_time":12.90451633,"remaining_time":13.37759433},
{"learn":[0.01588979481],"iteration":491,"passed_time":12.92945837,"remaining_time":13.34992857},
{"learn":[0.01585086757],"iteration":492,"passed_time":12.95764075,"remaining_time":13.32560621},
{"learn":[0.01581094616],"iteration":493,"passed_time":12.98450729,"remaining_time":13.29992042},
{"learn":[0.01575952831],"iteration":494,"passed_time":13.01920912,"remaining_time":13.28222345},
{"learn":[0.01572498137],"iteration":495,"passed_time":13.04608917,"remaining_time":13.25650996},
{"learn":[0.01569746902],"iteration":496,"passed_time":13.06774462,"remaining_time":13.22550412},
{"learn":[0.01564858366],"iteration":497,"passed_time":13.09668996,"remaining_time":13.20188426},
{"learn":[0.01562124336],"iteration":498,"passed_time":13.12302283,"remaining_time":13.17562012},
{"learn":[0.01559604479],"iteration":499,"passed_time":13.14385196,"remaining_time":13.14385196},
{"learn":[0.01556553971],"iteration":500,"passed_time":13.17231158,"remaining_time":13.11972751},
{"learn":[0.0155223513],"iteration":501,"passed_time":13.20113958,"remaining_time":13.09595122},
{"learn":[0.01545893526],"iteration":502,"passed_time":13.23313325,"remaining_time":13.07528275},
{"learn":[0.01540905359],"iteration":503,"passed_time":13.26370312,"remaining_time":13.05316815},
{"learn":[0.01536614965],"iteration":504,"passed_time":13.29273846,"remaining_time":13.02951591},
{"learn":[0.01533315631],"iteration":505,"passed_time":13.32168075,"remaining_time":13.00575156},
{"learn":[0.01527889597],"iteration":506,"passed_time":13.35054533,"remaining_time":12.98189122},
{"learn":[0.01523995408],"iteration":507,"passed_time":13.37771162,"remaining_time":12.95636638},
{"learn":[0.01520100447],"iteration":508,"passed_time":13.40630463,"remaining_time":12.93221134},
{"learn":[0.01515280446],"iteration":509,"passed_time":13.43467454,"remaining_time":12.90782456},
{"learn":[0.01510019384],"iteration":510,"passed_time":13.46154554,"remaining_time":12.88198781},
{"learn":[0.01505408977],"iteration":511,"passed_time":13.49468825,"remaining_time":12.86212474},
{"learn":[0.01501998871],"iteration":512,"passed_time":13.52218671,"remaining_time":12.83685171},
{"learn":[0.01499068611],"iteration":513,"passed_time":13.55198642,"remaining_time":12.81374591},
{"learn":[0.01495647676],"iteration":514,"passed_time":13.57802971,"remaining_time":12.78707652},
{"learn":[0.01489361037],"iteration":515,"passed_time":13.61087617,"remaining_time":12.76679082},
{"learn":[0.01486475688],"iteration":516,"passed_time":13.63554946,"remaining_time":12.73882087},
{"learn":[0.01483421774],"iteration":517,"passed_time":13.65984163,"remaining_time":12.710509},
{"learn":[0.01481494181],"iteration":518,"passed_time":13.68161296,"remaining_time":12.67987636},
{"learn":[0.01479858206],"iteration":519,"passed_time":13.70063429,"remaining_time":12.64673935},
{"learn":[0.01476683994],"iteration":520,"passed_time":13.72486979,"remaining_time":12.61845035},
{"learn":[0.01475294995],"iteration":521,"passed_time":13.74960604,"remaining_time":12.59063542},
{"learn":[0.01472135499],"iteration":522,"passed_time":13.77747188,"remaining_time":12.56568659},
{"learn":[0.0146785183],"iteration":523,"passed_time":13.80090683,"remaining_time":12.53670163},
{"learn":[0.01465548422],"iteration":524,"passed_time":13.83363488,"remaining_time":12.51614584},
{"learn":[0.01461904572],"iteration":525,"passed_time":13.86291758,"remaining_time":12.49243904},
{"learn":[0.01458886378],"iteration":526,"passed_time":13.88707717,"remaining_time":12.4641129},
{"learn":[0.01454849816],"iteration":527,"passed_time":13.91244858,"remaining_time":12.43688585},
{"learn":[0.01453159614],"iteration":528,"passed_time":13.93942513,"remaining_time":12.41109496},
{"learn":[0.01450993464],"iteration":529,"passed_time":13.96215192,"remaining_time":12.38153094},
{"learn":[0.01448254103],"iteration":530,"passed_time":13.99049738,"remaining_time":12.35695531},
{"learn":[0.01443241213],"iteration":531,"passed_time":14.01387329,"remaining_time":12.3279938},
{"learn":[0.01441429937],"iteration":532,"passed_time":14.04069475,"remaining_time":12.30207214},
{"learn":[0.01438348513],"iteration":533,"passed_time":14.06716679,"remaining_time":12.27584218},
{"learn":[0.01435307134],"iteration":534,"passed_time":14.09474292,"remaining_time":12.25057095},
{"learn":[0.01433121891],"iteration":535,"passed_time":14.12089633,"remaining_time":12.22405951},
{"learn":[0.01430684644],"iteration":536,"passed_time":14.14590375,"remaining_time":12.19656133},
{"learn":[0.01426861758],"iteration":537,"passed_time":14.17188325,"remaining_time":12.16990718},
{"learn":[0.01424512752],"iteration":538,"passed_time":14.19414142,"remaining_time":12.14007271},
{"learn":[0.01420120292],"iteration":539,"passed_time":14.22126983,"remaining_time":12.11441504},
{"learn":[0.01418770694],"iteration":540,"passed_time":14.24351621,"remaining_time":12.08460987},
{"learn":[0.01416313805],"iteration":541,"passed_time":14.26644142,"remaining_time":12.05540622},
{"learn":[0.01413877089],"iteration":542,"passed_time":14.29312133,"remaining_time":12.02938573},
{"learn":[0.01411219731],"iteration":543,"passed_time":14.32167925,"remaining_time":12.00493702},
{"learn":[0.0140980466],"iteration":544,"passed_time":14.34402771,"remaining_time":11.97528919},
{"learn":[0.01408183953],"iteration":545,"passed_time":14.37118308,"remaining_time":11.94966505},
{"learn":[0.01405962559],"iteration":546,"passed_time":14.39758529,"remaining_time":11.92341159},
{"learn":[0.01404518849],"iteration":547,"passed_time":14.42048538,"remaining_time":11.89426896},
{"learn":[0.01401251674],"iteration":548,"passed_time":14.4484345,"remaining_time":11.86929683},
{"learn":[0.0140045518],"iteration":549,"passed_time":14.47064667,"remaining_time":11.83962},
{"learn":[0.01399169958],"iteration":550,"passed_time":14.49447771,"remaining_time":11.81128946},
{"learn":[0.01396251794],"iteration":551,"passed_time":14.52357408,"remaining_time":11.78724853},
{"learn":[0.01391706764],"iteration":552,"passed_time":14.55309217,"remaining_time":11.7635302},
{"learn":[0.01389514826],"iteration":553,"passed_time":14.57932975,"remaining_time":11.73714994},
{"learn":[0.01386322565],"iteration":554,"passed_time":14.60688308,"remaining_time":11.71182517},
{"learn":[0.01383670679],"iteration":555,"passed_time":14.62901333,"remaining_time":11.68216173},
{"learn":[0.01380651409],"iteration":556,"passed_time":14.65582037,"remaining_time":11.65624493},
{"learn":[0.0137760589],"iteration":557,"passed_time":14.68484742,"remaining_time":11.63208344},
{"learn":[0.01374421208],"iteration":558,"passed_time":14.71081275,"remaining_time":11.60548913},
{"learn":[0.0137286097],"iteration":559,"passed_time":14.73624779,"remaining_time":11.57848041},
{"learn":[0.01370337956],"iteration":560,"passed_time":14.76195379,"remaining_time":11.55168933},
{"learn":[0.01367289789],"iteration":561,"passed_time":14.79102312,"remaining_time":11.52752336},
{"learn":[0.01364567816],"iteration":562,"passed_time":14.82100612,"remaining_time":11.50404916},
{"learn":[0.01362686432],"iteration":563,"passed_time":14.84234729,"remaining_time":11.47387131},
{"learn":[0.01359993743],"iteration":564,"passed_time":14.87187479,"remaining_time":11.45002749},
{"learn":[0.01354738835],"iteration":565,"passed_time":14.90131854,"remaining_time":11.42609938},
{"learn":[0.01353304171],"iteration":566,"passed_time":14.92613437,"remaining_time":11.39861761},
{"learn":[0.01351713135],"iteration":567,"passed_time":14.95172125,"remaining_time":11.37173165},
{"learn":[0.01349436997],"iteration":568,"passed_time":14.97757771,"remaining_time":11.34505447},
{"learn":[0.01344616445],"iteration":569,"passed_time":15.00898754,"remaining_time":11.32256955},
{"learn":[0.01342352144],"iteration":570,"passed_time":15.03366637,"remaining_time":11.29499628},
{"learn":[0.01340410706],"iteration":571,"passed_time":15.05789721,"remaining_time":11.26709791},
{"learn":[0.013388015],"iteration":572,"passed_time":15.08174917,"remaining_time":11.23893001},
{"learn":[0.01337831425],"iteration":573,"passed_time":15.10122208,"remaining_time":11.20752719},
{"learn":[0.01335505149],"iteration":574,"passed_time":15.12605492,"remaining_time":11.18012755},
{"learn":[0.01331944405],"iteration":575,"passed_time":15.155306,"remaining_time":11.15598914},
{"learn":[0.01329038278],"iteration":576,"passed_time":15.17986392,"remaining_time":11.12839244},
{"learn":[0.01329036254],"iteration":577,"passed_time":15.19616412,"remaining_time":11.09477727},
{"learn":[0.01327207887],"iteration":578,"passed_time":15.22017021,"remaining_time":11.06682497},
{"learn":[0.01324531753],"iteration":579,"passed_time":15.24734271,"remaining_time":11.0411792},
{"learn":[0.01321260136],"iteration":580,"passed_time":15.27109637,"remaining_time":11.01306262},
{"learn":[0.01318037981],"iteration":581,"passed_time":15.30045079,"remaining_time":10.98898356},
{"learn":[0.01316405604],"iteration":582,"passed_time":15.32205567,"remaining_time":10.95934342},
{"learn":[0.01313179592],"iteration":583,"passed_time":15.35078142,"remaining_time":10.9348032},
{"learn":[0.01311762262],"iteration":584,"passed_time":15.37037325,"remaining_time":10.90376906},
{"learn":[0.01310596611],"iteration":585,"passed_time":15.39334542,"remaining_time":10.87516212},
{"learn":[0.01309034194],"iteration":586,"passed_time":15.41686312,"remaining_time":10.84695821},
{"learn":[0.01307175901],"iteration":587,"passed_time":15.43957083,"remaining_time":10.81820269},
{"learn":[0.01304434285],"iteration":588,"passed_time":15.47095637,"remaining_time":10.79552304},
{"learn":[0.01302537387],"iteration":589,"passed_time":15.49596958,"remaining_time":10.76838564},
{"learn":[0.0129961541],"iteration":590,"passed_time":15.523993,"remaining_time":10.74333864},
{"learn":[0.01296653942],"iteration":591,"passed_time":15.55115204,"remaining_time":10.71768587},
{"learn":[0.01293758239],"iteration":592,"passed_time":15.57924225,"remaining_time":10.69266711},
{"learn":[0.01290132882],"iteration":593,"passed_time":15.60636896,"remaining_time":10.66697946},
{"learn":[0.01285833772],"iteration":594,"passed_time":15.63637692,"remaining_time":10.64324815},
{"learn":[0.01282251808],"iteration":595,"passed_time":15.65965433,"remaining_time":10.61493347},
{"learn":[0.01279580959],"iteration":596,"passed_time":15.68363942,"remaining_time":10.58711338},
{"learn":[0.01279063539],"iteration":597,"passed_time":15.70143229,"remaining_time":10.55514345},
{"learn":[0.01276478725],"iteration":598,"passed_time":15.72878796,"remaining_time":10.52962266},
{"learn":[0.01273739925],"iteration":599,"passed_time":15.75438187,"remaining_time":10.50292125},
{"learn":[0.01272074198],"iteration":600,"passed_time":15.77852067,"remaining_time":10.47525748},
{"learn":[0.01269711369],"iteration":601,"passed_time":15.80331629,"remaining_time":10.44803967},
{"learn":[0.01265339567],"iteration":602,"passed_time":15.83103283,"remaining_time":10.42275296},
{"learn":[0.01263488334],"iteration":603,"passed_time":15.85378208,"remaining_time":10.3942015},
{"learn":[0.01262691477],"iteration":604,"passed_time":15.87230883,"remaining_time":10.36291238},
{"learn":[0.01260553446],"iteration":605,"passed_time":15.89854483,"remaining_time":10.33667766},
{"learn":[0.01259148549],"iteration":606,"passed_time":15.92157083,"remaining_time":10.30836464},
{"learn":[0.01257523027],"iteration":607,"passed_time":15.94206496,"remaining_time":10.27843662},
{"learn":[0.01253421553],"iteration":608,"passed_time":15.97005387,"remaining_time":10.2533515},
{"learn":[0.01250890317],"iteration":609,"passed_time":16.00129512,"remaining_time":10.23033623},
{"learn":[0.01249607616],"iteration":610,"passed_time":16.02114667,"remaining_time":10.20004264},
{"learn":[0.01246449413],"iteration":611,"passed_time":16.04960996,"remaining_time":10.17524291},
{"learn":[0.01242313875],"iteration":612,"passed_time":16.07980404,"remaining_time":10.15152392},
{"learn":[0.01240857203],"iteration":613,"passed_time":16.10450817,"remaining_time":10.1243325},
{"learn":[0.01238376023],"iteration":614,"passed_time":16.12891579,"remaining_time":10.09696354},
{"learn":[0.01236365898],"iteration":615,"passed_time":16.15621504,"remaining_time":10.07140678},
{"learn":[0.01232986162],"iteration":616,"passed_time":16.18314525,"remaining_time":10.04561528},
{"learn":[0.01231562486],"iteration":617,"passed_time":16.20498504,"remaining_time":10.0166736},
{"learn":[0.01228783249],"iteration":618,"passed_time":16.23171921,"remaining_time":9.990767396},
{"learn":[0.012274708],"iteration":619,"passed_time":16.25684667,"remaining_time":9.963873763},
{"learn":[0.01226742257],"iteration":620,"passed_time":16.2773695,"remaining_time":9.934175589},
{"learn":[0.01225623165],"iteration":621,"passed_time":16.30069963,"remaining_time":9.906212955},
{"learn":[0.01223654901],"iteration":622,"passed_time":16.32666658,"remaining_time":9.879860838},
{"learn":[0.01221204386],"iteration":623,"passed_time":16.34974292,"remaining_time":9.851768168},
{"learn":[0.01217689951],"iteration":624,"passed_time":16.37901454,"remaining_time":9.827408725},
{"learn":[0.01215309486],"iteration":625,"passed_time":16.40945008,"remaining_time":9.803728964},
{"learn":[0.0121384547],"iteration":626,"passed_time":16.43505488,"remaining_time":9.777153857},
{"learn":[0.01212925368],"iteration":627,"passed_time":16.45799663,"remaining_time":9.74900437},
{"learn":[0.0121192059],"iteration":628,"passed_time":16.48055354,"remaining_time":9.720644458},
{"learn":[0.01210529258],"iteration":629,"passed_time":16.50474371,"remaining_time":9.693262178},
{"learn":[0.01207495424],"iteration":630,"passed_time":16.53421929,"remaining_time":9.668980854},
{"learn":[0.0120477625],"iteration":631,"passed_time":16.56362029,"remaining_time":9.644639664},
{"learn":[0.01202993381],"iteration":632,"passed_time":16.59222179,"remaining_time":9.619818953},
{"learn":[0.01201991676],"iteration":633,"passed_time":16.61800379,"remaining_time":9.593358656},
{"learn":[0.01200827662],"iteration":634,"passed_time":16.64089913,"remaining_time":9.565241229},
{"learn":[0.01199969498],"iteration":635,"passed_time":16.665899,"remaining_time":9.538344711},
{"learn":[0.01198834035],"iteration":636,"passed_time":16.69188,"remaining_time":9.51201325},
{"learn":[0.01196586273],"iteration":637,"passed_time":16.7213015,"remaining_time":9.48763502},
{"learn":[0.01194594161],"iteration":638,"passed_time":16.74098038,"remaining_time":9.457736957},
{"learn":[0.0119333826],"iteration":639,"passed_time":16.76716321,"remaining_time":9.431529305},
{"learn":[0.01191031055],"iteration":640,"passed_time":16.79474308,"remaining_time":9.406104161},
{"learn":[0.01189409555],"iteration":641,"passed_time":16.82017242,"remaining_time":9.379473092},
{"learn":[0.0118712882],"iteration":642,"passed_time":16.84588013,"remaining_time":9.353000318},
{"learn":[0.01185073557],"iteration":643,"passed_time":16.87285204,"remaining_time":9.327228768},
{"learn":[0.01183500268],"iteration":644,"passed_time":16.89643942,"remaining_time":9.299590687},
{"learn":[0.01181652905],"iteration":645,"passed_time":16.92195208,"remaining_time":9.273020182},
{"learn":[0.01181652033],"iteration":646,"passed_time":16.943162,"remaining_time":9.244105388},
{"learn":[0.01180922807],"iteration":647,"passed_time":16.96223117,"remaining_time":9.214051498},
{"learn":[0.01178616001],"iteration":648,"passed_time":16.98891442,"remaining_time":9.188149399},
{"learn":[0.01176703632],"iteration":649,"passed_time":17.01706538,"remaining_time":9.163035202},
{"learn":[0.0117519696],"iteration":650,"passed_time":17.044167,"remaining_time":9.137349129},
{"learn":[0.01174535646],"iteration":651,"passed_time":17.06703538,"remaining_time":9.109399249},
{"learn":[0.01172972758],"iteration":652,"passed_time":17.09511633,"remaining_time":9.084234866},
{"learn":[0.01171183974],"iteration":653,"passed_time":17.12046763,"remaining_time":9.057617429},
{"learn":[0.01169972642],"iteration":654,"passed_time":17.14043117,"remaining_time":9.028166034},
{"learn":[0.01168586336],"iteration":655,"passed_time":17.16727892,"remaining_time":9.002353578},
{"learn":[0.01166457833],"iteration":656,"passed_time":17.1924375,"remaining_time":8.975656107},
{"learn":[0.01166438257],"iteration":657,"passed_time":17.21339142,"remaining_time":8.94677791},
{"learn":[0.01164958416],"iteration":658,"passed_time":17.23822958,"remaining_time":8.919933669},
{"learn":[0.01162155884],"iteration":659,"passed_time":17.26906254,"remaining_time":8.896183734},
{"learn":[0.01160907563],"iteration":660,"passed_time":17.29351467,"remaining_time":8.869139897},
{"learn":[0.01158936781],"iteration":661,"passed_time":17.32304942,"remaining_time":8.844698947},
{"learn":[0.01157529495],"iteration":662,"passed_time":17.34746458,"remaining_time":8.817640369},
{"learn":[0.01157529031],"iteration":663,"passed_time":17.37276992,"remaining_time":8.791040199},
{"learn":[0.01156642313],"iteration":664,"passed_time":17.39241921,"remaining_time":8.761594639},
{"learn":[0.01154561076],"iteration":665,"passed_time":17.41857258,"remaining_time":8.735440305},
{"learn":[0.01153611202],"iteration":666,"passed_time":17.43861038,"remaining_time":8.706232766},
{"learn":[0.01153012339],"iteration":667,"passed_time":17.45717921,"remaining_time":8.676322601},
{"learn":[0.01152686539],"iteration":668,"passed_time":17.47972017,"remaining_time":8.648411622},
{"learn":[0.01151342612],"iteration":669,"passed_time":17.50036513,"remaining_time":8.619582823},
{"learn":[0.01150130574],"iteration":670,"passed_time":17.52499404,"remaining_time":8.592731803},
{"learn":[0.01148824714],"iteration":671,"passed_time":17.55124188,"remaining_time":8.566677582},
{"learn":[0.01148824069],"iteration":672,"passed_time":17.57045142,"remaining_time":8.537202991},
{"learn":[0.01148010154],"iteration":673,"passed_time":17.59640321,"remaining_time":8.511019949},
{"learn":[0.01146163065],"iteration":674,"passed_time":17.62026946,"remaining_time":8.483833443},
{"learn":[0.01145318453],"iteration":675,"passed_time":17.64571208,"remaining_time":8.4574123},
{"learn":[0.01144059478],"iteration":676,"passed_time":17.66643942,"remaining_time":8.42874436},
{"learn":[0.01142752887],"iteration":677,"passed_time":17.69296092,"remaining_time":8.402851645},
{"learn":[0.01139693474],"iteration":678,"passed_time":17.724771,"remaining_time":8.379457277},
{"learn":[0.01138202191],"iteration":679,"passed_time":17.75029938,"remaining_time":8.353082059},
{"learn":[0.01135269982],"iteration":680,"passed_time":17.78275033,"remaining_time":8.329952065},
{"learn":[0.01133126264],"iteration":681,"passed_time":17.80975992,"remaining_time":8.304257556},
{"learn":[0.01132321823],"iteration":682,"passed_time":17.83388488,"remaining_time":8.277220359},
{"learn":[0.01131210016],"iteration":683,"passed_time":17.85974992,"remaining_time":8.250995576},
{"learn":[0.01129269619],"iteration":684,"passed_time":17.88600913,"remaining_time":8.224953101},
{"learn":[0.01126802089],"iteration":685,"passed_time":17.91182708,"remaining_time":8.198708024},
{"learn":[0.01125823734],"iteration":686,"passed_time":17.92903963,"remaining_time":8.168543526},
{"learn":[0.01124478321],"iteration":687,"passed_time":17.95269179,"remaining_time":8.141336975},
{"learn":[0.011235996],"iteration":688,"passed_time":17.97333558,"remaining_time":8.112782825},
{"learn":[0.0112107135],"iteration":689,"passed_time":18.00104354,"remaining_time":8.087425359},
{"learn":[0.01119960741],"iteration":690,"passed_time":18.02383408,"remaining_time":8.05986213},
{"learn":[0.01118695928],"iteration":691,"passed_time":18.05121983,"remaining_time":8.034357961},
{"learn":[0.01117175172],"iteration":692,"passed_time":18.07317838,"remaining_time":8.0064441},
{"learn":[0.01115277022],"iteration":693,"passed_time":18.10068942,"remaining_time":7.980995622},
{"learn":[0.01114550998],"iteration":694,"passed_time":18.12024446,"remaining_time":7.952049726},
{"learn":[0.01112766016],"iteration":695,"passed_time":18.14952454,"remaining_time":7.927378535},
{"learn":[0.01111169426],"iteration":696,"passed_time":18.17356538,"remaining_time":7.900416512},
{"learn":[0.01109354003],"iteration":697,"passed_time":18.20230379,"remaining_time":7.875495337},
{"learn":[0.01108121389],"iteration":698,"passed_time":18.2282935,"remaining_time":7.849379604},
{"learn":[0.01107079505],"iteration":699,"passed_time":18.25235013,"remaining_time":7.822435768},
{"learn":[0.0110358998],"iteration":700,"passed_time":18.28060413,"remaining_time":7.79729049},
{"learn":[0.01101406595],"iteration":701,"passed_time":18.30676442,"remaining_time":7.771247573},
{"learn":[0.01100392946],"iteration":702,"passed_time":18.33150079,"remaining_time":7.744602753},
{"learn":[0.0109843374],"iteration":703,"passed_time":18.35985904,"remaining_time":7.719486188},
{"learn":[0.01097706517],"iteration":704,"passed_time":18.38475496,"remaining_time":7.692911649},
{"learn":[0.01096766189],"iteration":705,"passed_time":18.41127113,"remaining_time":7.667016587},
{"learn":[0.0109638886],"iteration":706,"passed_time":18.43694458,"remaining_time":7.640770527},
{"learn":[0.01094942848],"iteration":707,"passed_time":18.46232246,"remaining_time":7.614404178},
{"learn":[0.01092079051],"iteration":708,"passed_time":18.48970438,"remaining_time":7.58886315},
{"learn":[0.01091060737],"iteration":709,"passed_time":18.51175238,"remaining_time":7.561138294},
{"learn":[0.01090680327],"iteration":710,"passed_time":18.53764338,"remaining_time":7.53499147},
{"learn":[0.01089513537],"iteration":711,"passed_time":18.56247008,"remaining_time":7.508414865},
{"learn":[0.01088248017],"iteration":712,"passed_time":18.59191892,"remaining_time":7.483703687},
{"learn":[0.01087393598],"iteration":713,"passed_time":18.61671013,"remaining_time":7.457113579},
{"learn":[0.0108611392],"iteration":714,"passed_time":18.64322167,"remaining_time":7.431214231},
{"learn":[0.01084924636],"iteration":715,"passed_time":18.66867871,"remaining_time":7.404894907},
{"learn":[0.01084373453],"iteration":716,"passed_time":18.68961388,"remaining_time":7.376793203},
{"learn":[0.01082869434],"iteration":717,"passed_time":18.71612021,"remaining_time":7.35089958},
{"learn":[0.01082865785],"iteration":718,"passed_time":18.73405588,"remaining_time":7.32165466},
{"learn":[0.01081457954],"iteration":719,"passed_time":18.75975746,"remaining_time":7.295461234},
{"learn":[0.0108072327],"iteration":720,"passed_time":18.78394079,"remaining_time":7.268681666},
{"learn":[0.0108072212],"iteration":721,"passed_time":18.79987192,"remaining_time":7.238731846},
{"learn":[0.01079370957],"iteration":722,"passed_time":18.82717129,"remaining_time":7.213176276},
{"learn":[0.01078173232],"iteration":723,"passed_time":18.85298879,"remaining_time":7.187050976},
{"learn":[0.01076821113],"iteration":724,"passed_time":18.87729067,"remaining_time":7.160351632},
{"learn":[0.01076819922],"iteration":725,"passed_time":18.89581813,"remaining_time":7.131479568},
{"learn":[0.01074670304],"iteration":726,"passed_time":18.92743413,"remaining_time":7.107550916},
{"learn":[0.01073682556],"iteration":727,"passed_time":18.95328021,"remaining_time":7.081445353},
{"learn":[0.01073681302],"iteration":728,"passed_time":18.97088642,"remaining_time":7.052277392},
{"learn":[0.01072962646],"iteration":729,"passed_time":18.99774013,"remaining_time":7.026561416},
{"learn":[0.01071860132],"iteration":730,"passed_time":19.02314229,"remaining_time":7.000308176},
{"learn":[0.01071224735],"iteration":731,"passed_time":19.04634967,"remaining_time":6.973253703},
{"learn":[0.01068878728],"iteration":732,"passed_time":19.073078,"remaining_time":6.947492259},
{"learn":[0.01067319465],"iteration":733,"passed_time":19.1028705,"remaining_time":6.922838628},
{"learn":[0.01067317113],"iteration":734,"passed_time":19.1252715,"remaining_time":6.895506051},
{"learn":[0.01066512085],"iteration":735,"passed_time":19.15011533,"remaining_time":6.869063109},
{"learn":[0.01065764835],"iteration":736,"passed_time":19.17246767,"remaining_time":6.841735409},
{"learn":[0.01065402045],"iteration":737,"passed_time":19.19475,"remaining_time":6.814396341},
{"learn":[0.01064096327],"iteration":738,"passed_time":19.22135288,"remaining_time":6.788596888},
{"learn":[0.01062632784],"iteration":739,"passed_time":19.24895183,"remaining_time":6.763145239},
{"learn":[0.01062055504],"iteration":740,"passed_time":19.27201254,"remaining_time":6.73610155},
{"learn":[0.01061106306],"iteration":741,"passed_time":19.29152017,"remaining_time":6.707833158},
{"learn":[0.01061105844],"iteration":742,"passed_time":19.31140208,"remaining_time":6.679717813},
{"learn":[0.01061106422],"iteration":743,"passed_time":19.32812554,"remaining_time":6.650537821},
{"learn":[0.01059677264],"iteration":744,"passed_time":19.35460538,"remaining_time":6.624730699},
{"learn":[0.01057702665],"iteration":745,"passed_time":19.38349725,"remaining_time":6.599743032},
{"learn":[0.01056441578],"iteration":746,"passed_time":19.41002329,"remaining_time":6.573943632},
{"learn":[0.01056441387],"iteration":747,"passed_time":19.42875342,"remaining_time":6.545515857},
{"learn":[0.01056439374],"iteration":748,"passed_time":19.44987938,"remaining_time":6.517916853},
{"learn":[0.01054763598],"iteration":749,"passed_time":19.47541408,"remaining_time":6.491804694},
{"learn":[0.01053219177],"iteration":750,"passed_time":19.50053454,"remaining_time":6.465556726},
{"learn":[0.01053218703],"iteration":751,"passed_time":19.51646213,"remaining_time":6.436280063},
{"learn":[0.01050880037],"iteration":752,"passed_time":19.547426,"remaining_time":6.411971078},
{"learn":[0.01050877363],"iteration":753,"passed_time":19.57053813,"remaining_time":6.38508273},
{"learn":[0.01050027801],"iteration":754,"passed_time":19.59367633,"remaining_time":6.35821285},
{"learn":[0.01048819503],"iteration":755,"passed_time":19.62088925,"remaining_time":6.332667959},
{"learn":[0.01048818025],"iteration":756,"passed_time":19.64119688,"remaining_time":6.304902035},
{"learn":[0.01048363736],"iteration":757,"passed_time":19.659593,"remaining_time":6.276545522},
{"learn":[0.01047163962],"iteration":758,"passed_time":19.6880095,"remaining_time":6.251396956},
{"learn":[0.01045863841],"iteration":759,"passed_time":19.71550129,"remaining_time":6.225947776},
{"learn":[0.01045862421],"iteration":760,"passed_time":19.73758642,"remaining_time":6.198795208},
{"learn":[0.01045857914],"iteration":761,"passed_time":19.75617963,"remaining_time":6.17056529},
{"learn":[0.01043478827],"iteration":762,"passed_time":19.78523204,"remaining_time":6.145609428},
{"learn":[0.010426201],"iteration":763,"passed_time":19.808413,"remaining_time":6.118829147},
{"learn":[0.01042618422],"iteration":764,"passed_time":19.82708654,"remaining_time":6.090673644},
{"learn":[0.01040720785],"iteration":765,"passed_time":19.85120088,"remaining_time":6.064204967},
{"learn":[0.01040720657],"iteration":766,"passed_time":19.87165192,"remaining_time":6.036629591},
{"learn":[0.01039536668],"iteration":767,"passed_time":19.89677104,"remaining_time":6.010482919},
{"learn":[0.01039537068],"iteration":768,"passed_time":19.918155,"remaining_time":5.983216912},
{"learn":[0.01037541191],"iteration":769,"passed_time":19.94736663,"remaining_time":5.958304317},
{"learn":[0.01037536513],"iteration":770,"passed_time":19.96922908,"remaining_time":5.931197743},
{"learn":[0.01035017525],"iteration":771,"passed_time":19.99878996,"remaining_time":5.906378381},
{"learn":[0.01035004265],"iteration":772,"passed_time":20.01617388,"remaining_time":5.877970853},
{"learn":[0.01035000668],"iteration":773,"passed_time":20.03834021,"remaining_time":5.850988226},
{"learn":[0.01032974052],"iteration":774,"passed_time":20.06799083,"remaining_time":5.826190887},
{"learn":[0.01030795161],"iteration":775,"passed_time":20.09887925,"remaining_time":5.80173834},
{"learn":[0.01030154674],"iteration":776,"passed_time":20.12835846,"remaining_time":5.776864783},
{"learn":[0.01028246875],"iteration":777,"passed_time":20.16038933,"remaining_time":5.752707496},
{"learn":[0.01026982316],"iteration":778,"passed_time":20.18874904,"remaining_time":5.727488496},
{"learn":[0.01026980539],"iteration":779,"passed_time":20.20572888,"remaining_time":5.699051734},
{"learn":[0.01024686451],"iteration":780,"passed_time":20.23221788,"remaining_time":5.673310774},
{"learn":[0.01024032995],"iteration":781,"passed_time":20.25823708,"remaining_time":5.647436936},
{"learn":[0.01023798929],"iteration":782,"passed_time":20.28051229,"remaining_time":5.620525118},
{"learn":[0.01022591318],"iteration":783,"passed_time":20.30665417,"remaining_time":5.594690434},
{"learn":[0.01021188891],"iteration":784,"passed_time":20.32940683,"remaining_time":5.567926712},
{"learn":[0.01019633586],"iteration":785,"passed_time":20.35462879,"remaining_time":5.541845498},
{"learn":[0.01018575405],"iteration":786,"passed_time":20.38161813,"remaining_time":5.516244804},
{"learn":[0.01017598252],"iteration":787,"passed_time":20.40976483,"remaining_time":5.49095196},
{"learn":[0.01015863017],"iteration":788,"passed_time":20.43922442,"remaining_time":5.466002981},
{"learn":[0.01015860299],"iteration":789,"passed_time":20.45983013,"remaining_time":5.438689021},
{"learn":[0.01014595213],"iteration":790,"passed_time":20.48751363,"remaining_time":5.413262134},
{"learn":[0.01014588055],"iteration":791,"passed_time":20.50939971,"remaining_time":5.386306994},
{"learn":[0.01012766378],"iteration":792,"passed_time":20.53907429,"remaining_time":5.361397703},
{"learn":[0.01012021836],"iteration":793,"passed_time":20.55937404,"remaining_time":5.334044147},
{"learn":[0.0101090026],"iteration":794,"passed_time":20.58423263,"remaining_time":5.307883884},
{"learn":[0.01009926499],"iteration":795,"passed_time":20.608002,"remaining_time":5.281447749},
{"learn":[0.01007923517],"iteration":796,"passed_time":20.63607717,"remaining_time":5.256115012},
{"learn":[0.01007049624],"iteration":797,"passed_time":20.66296525,"remaining_time":5.230474913},
{"learn":[0.01005698496],"iteration":798,"passed_time":20.68663713,"remaining_time":5.204022606},
{"learn":[0.01004719453],"iteration":799,"passed_time":20.70864608,"remaining_time":5.177161521},
{"learn":[0.01003297559],"iteration":800,"passed_time":20.73740371,"remaining_time":5.151989186},
{"learn":[0.01001884572],"iteration":801,"passed_time":20.76544988,"remaining_time":5.126632263},
{"learn":[0.01001113511],"iteration":802,"passed_time":20.79387804,"remaining_time":5.101362359},
{"learn":[0.01000239495],"iteration":803,"passed_time":20.82170546,"remaining_time":5.075938147},
{"learn":[0.00999171123],"iteration":804,"passed_time":20.84965358,"remaining_time":5.050537203},
{"learn":[0.009991695347],"iteration":805,"passed_time":20.87272292,"remaining_time":5.02395564},
{"learn":[0.009991440922],"iteration":806,"passed_time":20.89614929,"remaining_time":4.99746817},
{"learn":[0.009976874063],"iteration":807,"passed_time":20.92422446,"remaining_time":4.972092941},
{"learn":[0.009971109178],"iteration":808,"passed_time":20.94461108,"remaining_time":4.944895818},
{"learn":[0.00996096955],"iteration":809,"passed_time":20.97035604,"remaining_time":4.918972405},
{"learn":[0.009952270277],"iteration":810,"passed_time":20.99332521,"remaining_time":4.892402545},
{"learn":[0.009942550832],"iteration":811,"passed_time":21.01712808,"remaining_time":4.866034581},
{"learn":[0.009936698196],"iteration":812,"passed_time":21.04029358,"remaining_time":4.839526322},
{"learn":[0.009936678407],"iteration":813,"passed_time":21.06232313,"remaining_time":4.812766709},
{"learn":[0.009929258088],"iteration":814,"passed_time":21.08629646,"remaining_time":4.786459932},
{"learn":[0.009919296204],"iteration":815,"passed_time":21.10853783,"remaining_time":4.759768335},
{"learn":[0.009909905467],"iteration":816,"passed_time":21.13112558,"remaining_time":4.733165216},
{"learn":[0.009909813327],"iteration":817,"passed_time":21.14843467,"remaining_time":4.705397444},
{"learn":[0.009901201002],"iteration":818,"passed_time":21.17453904,"remaining_time":4.679598982},
{"learn":[0.009887892108],"iteration":819,"passed_time":21.19929413,"remaining_time":4.653503588},
{"learn":[0.009881094023],"iteration":820,"passed_time":21.22231029,"remaining_time":4.627032329},
{"learn":[0.009868239006],"iteration":821,"passed_time":21.25231371,"remaining_time":4.602082531},
{"learn":[0.009849734902],"iteration":822,"passed_time":21.28028825,"remaining_time":4.576684107},
{"learn":[0.009849733376],"iteration":823,"passed_time":21.30360446,"remaining_time":4.550284447},
{"learn":[0.009849567214],"iteration":824,"passed_time":21.32394579,"remaining_time":4.523261229},
{"learn":[0.009849552724],"iteration":825,"passed_time":21.34927525,"remaining_time":4.497304956},
{"learn":[0.009839271482],"iteration":826,"passed_time":21.37662279,"remaining_time":4.471772361},
{"learn":[0.009832139675],"iteration":827,"passed_time":21.40014875,"remaining_time":4.445441528},
{"learn":[0.009823340344],"iteration":828,"passed_time":21.4202685,"remaining_time":4.418414853},
{"learn":[0.009823331839],"iteration":829,"passed_time":21.437008,"remaining_time":4.390712482},
{"learn":[0.009806600522],"iteration":830,"passed_time":21.46346558,"remaining_time":4.365012856},
{"learn":[0.009806533175],"iteration":831,"passed_time":21.49151988,"remaining_time":4.339633821},
{"learn":[0.009799329716],"iteration":832,"passed_time":21.51547125,"remaining_time":4.313425809},
{"learn":[0.009784812],"iteration":833,"passed_time":21.54388583,"remaining_time":4.288111569},
{"learn":[0.009774257733],"iteration":834,"passed_time":21.56779408,"remaining_time":4.26189943},
{"learn":[0.009774251519],"iteration":835,"passed_time":21.59081154,"remaining_time":4.235518054},
{"learn":[0.009765864759],"iteration":836,"passed_time":21.61397075,"remaining_time":4.20917232},
{"learn":[0.009761450711],"iteration":837,"passed_time":21.63871271,"remaining_time":4.183140166},
{"learn":[0.009752342097],"iteration":838,"passed_time":21.66651779,"remaining_time":4.157698885},
{"learn":[0.009750824759],"iteration":839,"passed_time":21.68713908,"remaining_time":4.130883635},
{"learn":[0.00973983994],"iteration":840,"passed_time":21.71329117,"remaining_time":4.10512877},
{"learn":[0.009725760043],"iteration":841,"passed_time":21.73559258,"remaining_time":4.07865039},
{"learn":[0.009712292794],"iteration":842,"passed_time":21.76332488,"remaining_time":4.053193363},
{"learn":[0.009712284972],"iteration":843,"passed_time":21.78570675,"remaining_time":4.026742006},
{"learn":[0.009701309398],"iteration":844,"passed_time":21.81458733,"remaining_time":4.001492351},
{"learn":[0.00970129987],"iteration":845,"passed_time":21.83405604,"remaining_time":3.97452084},
{"learn":[0.009689653929],"iteration":846,"passed_time":21.8636205,"remaining_time":3.949390716},
{"learn":[0.009689639042],"iteration":847,"passed_time":21.88629171,"remaining_time":3.923014551},
{"learn":[0.009674211132],"iteration":848,"passed_time":21.91602613,"remaining_time":3.897903351},
{"learn":[0.009667259166],"iteration":849,"passed_time":21.93849279,"remaining_time":3.871498728},
{"learn":[0.009658559792],"iteration":850,"passed_time":21.96425492,"remaining_time":3.845680356},
{"learn":[0.009658523918],"iteration":851,"passed_time":21.98742029,"remaining_time":3.819411037},
{"learn":[0.009658514937],"iteration":852,"passed_time":22.01222888,"remaining_time":3.793432174},
{"learn":[0.009653633565],"iteration":853,"passed_time":22.036348,"remaining_time":3.767338183},
{"learn":[0.009638763327],"iteration":854,"passed_time":22.067732,"remaining_time":3.742480865},
{"learn":[0.009622406961],"iteration":855,"passed_time":22.09706671,"remaining_time":3.717263558},
{"learn":[0.009622396495],"iteration":856,"passed_time":22.12206417,"remaining_time":3.691312924},
{"learn":[0.00962238999],"iteration":857,"passed_time":22.14057896,"remaining_time":3.664291622},
{"learn":[0.009611100959],"iteration":858,"passed_time":22.16600771,"remaining_time":3.638425014},
{"learn":[0.009597118169],"iteration":859,"passed_time":22.19183683,"remaining_time":3.612624601},
{"learn":[0.009589504915],"iteration":860,"passed_time":22.21878033,"remaining_time":3.587004026},
{"learn":[0.009569170459],"iteration":861,"passed_time":22.25436646,"remaining_time":3.562764004},
{"learn":[0.009559836821],"iteration":862,"passed_time":22.28175138,"remaining_time":3.537195757},
{"learn":[0.009545280228],"iteration":863,"passed_time":22.30691879,"remaining_time":3.511274254},
{"learn":[0.009534366821],"iteration":864,"passed_time":22.33462775,"remaining_time":3.485751152},
{"learn":[0.009524820524],"iteration":865,"passed_time":22.36211742,"remaining_time":3.460189069},
{"learn":[0.009517615275],"iteration":866,"passed_time":22.38521063,"remaining_time":3.433948112},
{"learn":[0.009508992216],"iteration":867,"passed_time":22.40787938,"remaining_time":3.407649859},
{"learn":[0.009508995862],"iteration":868,"passed_time":22.42451829,"remaining_time":3.380450974},
{"learn":[0.009501289981],"iteration":869,"passed_time":22.4488565,"remaining_time":3.354426833},
{"learn":[0.009493779826],"iteration":870,"passed_time":22.47891113,"remaining_time":3.329253198},
{"learn":[0.009493639505],"iteration":871,"passed_time":22.50080483,"remaining_time":3.302870434},
{"learn":[0.009484338245],"iteration":872,"passed_time":22.52442538,"remaining_time":3.276749167},
{"learn":[0.009484321961],"iteration":873,"passed_time":22.54434354,"remaining_time":3.25009987},
{"learn":[0.009484323025],"iteration":874,"passed_time":22.56919254,"remaining_time":3.224170363},
{"learn":[0.009476880429],"iteration":875,"passed_time":22.59201363,"remaining_time":3.197956267},
{"learn":[0.009476631887],"iteration":876,"passed_time":22.60923421,"remaining_time":3.170964433},
{"learn":[0.009466695969],"iteration":877,"passed_time":22.63659975,"remaining_time":3.145404521},
{"learn":[0.009455509257],"iteration":878,"passed_time":22.66628029,"remaining_time":3.120159176},
{"learn":[0.009451242539],"iteration":879,"passed_time":22.69300254,"remaining_time":3.094500347},
{"learn":[0.009451218727],"iteration":880,"passed_time":22.72177546,"remaining_time":3.069116095},
{"learn":[0.009442578726],"iteration":881,"passed_time":22.74097304,"remaining_time":3.042443105},
{"learn":[0.009431738919],"iteration":882,"passed_time":22.76779338,"remaining_time":3.016797084},
{"learn":[0.009431734667],"iteration":883,"passed_time":22.79034508,"remaining_time":2.990588269},
{"learn":[0.00943173125],"iteration":884,"passed_time":22.81400404,"remaining_time":2.964531599},
{"learn":[0.009431704376],"iteration":885,"passed_time":22.84053771,"remaining_time":2.938850224},
{"learn":[0.009411709503],"iteration":886,"passed_time":22.86938704,"remaining_time":2.913461934},
{"learn":[0.009386729729],"iteration":887,"passed_time":22.89934717,"remaining_time":2.888205949},
{"learn":[0.009386722322],"iteration":888,"passed_time":22.92050296,"remaining_time":2.861840077},
{"learn":[0.009375633622],"iteration":889,"passed_time":22.94995575,"remaining_time":2.836511385},
{"learn":[0.009375598928],"iteration":890,"passed_time":22.97516083,"remaining_time":2.810653794},
{"learn":[0.009364534393],"iteration":891,"passed_time":23.00448004,"remaining_time":2.78529579},
{"learn":[0.009364522878],"iteration":892,"passed_time":23.02785242,"remaining_time":2.759216359},
{"learn":[0.009364517202],"iteration":893,"passed_time":23.04766533,"remaining_time":2.732720946},
{"learn":[0.009354629517],"iteration":894,"passed_time":23.07821325,"remaining_time":2.707499878},
{"learn":[0.009346207523],"iteration":895,"passed_time":23.10128104,"remaining_time":2.681398692},
{"learn":[0.009346188678],"iteration":896,"passed_time":23.12011863,"remaining_time":2.654818527},
{"learn":[0.00932960525],"iteration":897,"passed_time":23.14789067,"remaining_time":2.629270432},
{"learn":[0.009329609668],"iteration":898,"passed_time":23.16511163,"remaining_time":2.602532007},
{"learn":[0.009301852181],"iteration":899,"passed_time":23.19466625,"remaining_time":2.577185139},
{"learn":[0.009301845075],"iteration":900,"passed_time":23.21981042,"remaining_time":2.551344319},
{"learn":[0.009295267315],"iteration":901,"passed_time":23.24697946,"remaining_time":2.525725041},
{"learn":[0.009295260678],"iteration":902,"passed_time":23.26924925,"remaining_time":2.499576055},
{"learn":[0.009295241682],"iteration":903,"passed_time":23.29180971,"remaining_time":2.473466518},
{"learn":[0.009284191493],"iteration":904,"passed_time":23.32042463,"remaining_time":2.448000375},
{"learn":[0.009284175205],"iteration":905,"passed_time":23.3404125,"remaining_time":2.421632202},
{"learn":[0.009275020844],"iteration":906,"passed_time":23.36627638,"remaining_time":2.395880599},
{"learn":[0.009274999643],"iteration":907,"passed_time":23.38957738,"remaining_time":2.369869073},
{"learn":[0.009267363071],"iteration":908,"passed_time":23.41122454,"remaining_time":2.343697946},
{"learn":[0.009263277166],"iteration":909,"passed_time":23.43469683,"remaining_time":2.317717269},
{"learn":[0.009263261172],"iteration":910,"passed_time":23.45559058,"remaining_time":2.291490189},
{"learn":[0.00926320682],"iteration":911,"passed_time":23.48198613,"remaining_time":2.265805679},
{"learn":[0.009263179811],"iteration":912,"passed_time":23.50481675,"remaining_time":2.239779909},
{"learn":[0.009251126906],"iteration":913,"passed_time":23.53357854,"remaining_time":2.214319206},
{"learn":[0.009239711568],"iteration":914,"passed_time":23.5639695,"remaining_time":2.189002631},
{"learn":[0.009239711568],"iteration":915,"passed_time":23.588541,"remaining_time":2.163141314},
{"learn":[0.009231001939],"iteration":916,"passed_time":23.61604867,"remaining_time":2.137548571},
{"learn":[0.009208348559],"iteration":917,"passed_time":23.64229396,"remaining_time":2.111838894},
{"learn":[0.009208294667],"iteration":918,"passed_time":23.66323446,"remaining_time":2.085660491},
{"learn":[0.009197960172],"iteration":919,"passed_time":23.6894615,"remaining_time":2.059953174},
{"learn":[0.009185486669],"iteration":920,"passed_time":23.71709608,"remaining_time":2.034365462},
{"learn":[0.009180256069],"iteration":921,"passed_time":23.74104029,"remaining_time":2.008461109},
{"learn":[0.009180061769],"iteration":922,"passed_time":23.76287946,"remaining_time":1.982385394},
{"learn":[0.00917026521],"iteration":923,"passed_time":23.79249242,"remaining_time":1.956958251},
{"learn":[0.00917025631],"iteration":924,"passed_time":23.81576758,"remaining_time":1.931008182},
{"learn":[0.009159602843],"iteration":925,"passed_time":23.84185579,"remaining_time":1.905288692},
{"learn":[0.009159556645],"iteration":926,"passed_time":23.86349229,"remaining_time":1.87921784},
{"learn":[0.009146612968],"iteration":927,"passed_time":23.88956942,"remaining_time":1.853501075},
{"learn":[0.00914660697],"iteration":928,"passed_time":23.90844058,"remaining_time":1.827232811},
{"learn":[0.009138491063],"iteration":929,"passed_time":23.93340479,"remaining_time":1.80143907},
{"learn":[0.009127774014],"iteration":930,"passed_time":23.95506642,"remaining_time":1.775402345},
{"learn":[0.009127747027],"iteration":931,"passed_time":23.97979375,"remaining_time":1.749598686},
{"learn":[0.00912065165],"iteration":932,"passed_time":24.00030054,"remaining_time":1.723494251},
{"learn":[0.009113805307],"iteration":933,"passed_time":24.02642521,"remaining_time":1.697798783},
{"learn":[0.009111257954],"iteration":934,"passed_time":24.05157954,"remaining_time":1.672034941},
{"learn":[0.009104199666],"iteration":935,"passed_time":24.07752221,"remaining_time":1.646326305},
{"learn":[0.009101263729],"iteration":936,"passed_time":24.100748,"remaining_time":1.620434497},
{"learn":[0.009099518318],"iteration":937,"passed_time":24.12723721,"remaining_time":1.59476408},
{"learn":[0.009099515353],"iteration":938,"passed_time":24.15301417,"remaining_time":1.569045649},
{"learn":[0.009099506736],"iteration":939,"passed_time":24.17371117,"remaining_time":1.54300284},
{"learn":[0.009099482158],"iteration":940,"passed_time":24.19560963,"remaining_time":1.517046725},
{"learn":[0.009099470198],"iteration":941,"passed_time":24.22785225,"remaining_time":1.491736126},
{"learn":[0.00909447715],"iteration":942,"passed_time":24.25065271,"remaining_time":1.465840089},
{"learn":[0.009094480791],"iteration":943,"passed_time":24.27335838,"remaining_time":1.439944988},
{"learn":[0.009084071208],"iteration":944,"passed_time":24.29475767,"remaining_time":1.413980605},
{"learn":[0.009079208523],"iteration":945,"passed_time":24.32017888,"remaining_time":1.388255454},
{"learn":[0.009079192809],"iteration":946,"passed_time":24.33769967,"remaining_time":1.362088788},
{"learn":[0.009079185837],"iteration":947,"passed_time":24.35888579,"remaining_time":1.336141415},
{"learn":[0.009079174668],"iteration":948,"passed_time":24.38593983,"remaining_time":1.310519422},
{"learn":[0.009066992805],"iteration":949,"passed_time":24.41219292,"remaining_time":1.284852259},
{"learn":[0.009066978157],"iteration":950,"passed_time":24.43317379,"remaining_time":1.258912214},
{"learn":[0.009061200189],"iteration":951,"passed_time":24.45752804,"remaining_time":1.233152674},
{"learn":[0.009061200827],"iteration":952,"passed_time":24.48019783,"remaining_time":1.20731301},
{"learn":[0.009048263697],"iteration":953,"passed_time":24.51132975,"remaining_time":1.181888017},
{"learn":[0.009048247018],"iteration":954,"passed_time":24.53988121,"remaining_time":1.156329481},
{"learn":[0.009048237389],"iteration":955,"passed_time":24.56879129,"remaining_time":1.130781189},
{"learn":[0.009029423034],"iteration":956,"passed_time":24.59986613,"remaining_time":1.105323138},
{"learn":[0.009020334877],"iteration":957,"passed_time":24.62725925,"remaining_time":1.07969195},
{"learn":[0.009020319722],"iteration":958,"passed_time":24.64403463,"remaining_time":1.053603149},
{"learn":[0.00901536658],"iteration":959,"passed_time":24.66927975,"remaining_time":1.027886656},
{"learn":[0.009008146256],"iteration":960,"passed_time":24.69145742,"remaining_time":1.002046659},
{"learn":[0.009008080923],"iteration":961,"passed_time":24.71403421,"remaining_time":0.9762300415},
{"learn":[0.008999092713],"iteration":962,"passed_time":24.74068379,"remaining_time":0.9505766358},
{"learn":[0.008999084096],"iteration":963,"passed_time":24.76208954,"remaining_time":0.9247253356},
{"learn":[0.008999061663],"iteration":964,"passed_time":24.78761367,"remaining_time":0.89903262},
{"learn":[0.008999057797],"iteration":965,"passed_time":24.80499763,"remaining_time":0.8730537466},
{"learn":[0.00898479139],"iteration":966,"passed_time":24.83401308,"remaining_time":0.8474895882},
{"learn":[0.008970760561],"iteration":967,"passed_time":24.86370271,"remaining_time":0.8219405854},
{"learn":[0.008955231722],"iteration":968,"passed_time":24.89336346,"remaining_time":0.7963821127},
{"learn":[0.008943778873],"iteration":969,"passed_time":24.92045067,"remaining_time":0.7707355876},
{"learn":[0.008943740035],"iteration":970,"passed_time":24.9432055,"remaining_time":0.7449567039},
{"learn":[0.008943723844],"iteration":971,"passed_time":24.96732338,"remaining_time":0.7192233071},
{"learn":[0.008927970783],"iteration":972,"passed_time":24.997568,"remaining_time":0.6936632436},
{"learn":[0.008919523889],"iteration":973,"passed_time":25.02311192,"remaining_time":0.6679680799},
{"learn":[0.008912990747],"iteration":974,"passed_time":25.04562554,"remaining_time":0.6421955267},
{"learn":[0.008898149437],"iteration":975,"passed_time":25.07549979,"remaining_time":0.6166106506},
{"learn":[0.008898149437],"iteration":976,"passed_time":25.09482733,"remaining_time":0.590768709},
{"learn":[0.008889112814],"iteration":977,"passed_time":25.11928029,"remaining_time":0.5650553849},
{"learn":[0.00887961815],"iteration":978,"passed_time":25.145738,"remaining_time":0.5393876384},
{"learn":[0.008877745765],"iteration":979,"passed_time":25.17115875,"remaining_time":0.5136971173},
{"learn":[0.008877677442],"iteration":980,"passed_time":25.19193229,"remaining_time":0.4879171392},
{"learn":[0.008865931762],"iteration":981,"passed_time":25.21862642,"remaining_time":0.4622558814},
{"learn":[0.008858768603],"iteration":982,"passed_time":25.24188308,"remaining_time":0.4365330747},
{"learn":[0.008848097428],"iteration":983,"passed_time":25.27109671,"remaining_time":0.4109121416},
{"learn":[0.008836826299],"iteration":984,"passed_time":25.30018792,"remaining_time":0.3852820495},
{"learn":[0.008831658808],"iteration":985,"passed_time":25.32461675,"remaining_time":0.3595787368},
{"learn":[0.008831655065],"iteration":986,"passed_time":25.34729071,"remaining_time":0.3338548928},
{"learn":[0.008815468345],"iteration":987,"passed_time":25.37696838,"remaining_time":0.308222288},
{"learn":[0.00881545437],"iteration":988,"passed_time":25.40420183,"remaining_time":0.2825543177},
{"learn":[0.008815450802],"iteration":989,"passed_time":25.42369929,"remaining_time":0.2568050434},
{"learn":[0.008805244774],"iteration":990,"passed_time":25.44454867,"remaining_time":0.231080664},
{"learn":[0.008805244774],"iteration":991,"passed_time":25.46088925,"remaining_time":0.205329752},
{"learn":[0.008791343686],"iteration":992,"passed_time":25.48991838,"remaining_time":0.1796872393},
{"learn":[0.00878342574],"iteration":993,"passed_time":25.51390879,"remaining_time":0.1540074977},
{"learn":[0.008783414552],"iteration":994,"passed_time":25.53472346,"remaining_time":0.1283151933},
{"learn":[0.008783404836],"iteration":995,"passed_time":25.55667604,"remaining_time":0.1026372532},
{"learn":[0.008774433995],"iteration":996,"passed_time":25.58438133,"remaining_time":0.07698409629},
{"learn":[0.008760689989],"iteration":997,"passed_time":25.61510013,"remaining_time":0.05133286598},
{"learn":[0.008760688554],"iteration":998,"passed_time":25.63743038,"remaining_time":0.02566309347},
{"learn":[0.008750235518],"iteration":999,"passed_time":25.666161,"remaining_time":0}
]}